{
  "version": "1.0",
  "items": [
    { "id": "letter_a",  "kind": "letter",   "symbol": "А", "strokes": [[{"x":0.20,"y":0.85},{"x":0.50,"y":0.15},{"x":0.80,"y":0.85}],[{"x":0.32,"y":0.55},{"x":0.68,"y":0.55}]] },
    { "id": "letter_b",  "kind": "letter",   "symbol": "Б", "strokes": [[{"x":0.30,"y":0.15},{"x":0.70,"y":0.15}],[{"x":0.30,"y":0.15},{"x":0.30,"y":0.85}],[{"x":0.30,"y":0.45},{"x":0.65,"y":0.45},{"x":0.75,"y":0.55},{"x":0.75,"y":0.75},{"x":0.65,"y":0.85},{"x":0.30,"y":0.85}]] },
    { "id": "letter_v",  "kind": "letter",   "symbol": "В", "strokes": [[{"x":0.30,"y":0.15},{"x":0.30,"y":0.85}],[{"x":0.30,"y":0.15},{"x":0.65,"y":0.15},{"x":0.75,"y":0.25},{"x":0.75,"y":0.40},{"x":0.65,"y":0.50},{"x":0.30,"y":0.50}],[{"x":0.30,"y":0.50},{"x":0.65,"y":0.50},{"x":0.75,"y":0.60},{"x":0.75,"y":0.75},{"x":0.65,"y":0.85},{"x":0.30,"y":0.85}]] },
    { "id": "letter_g",  "kind": "letter",   "symbol": "Г", "strokes": [[{"x":0.30,"y":0.85},{"x":0.30,"y":0.15},{"x":0.75,"y":0.15}]] },
    { "id": "letter_d",  "kind": "letter",   "symbol": "Д", "strokes": [[{"x":0.25,"y":0.85},{"x":0.25,"y":0.75},{"x":0.35,"y":0.75},{"x":0.35,"y":0.15},{"x":0.70,"y":0.15},{"x":0.70,"y":0.75},{"x":0.80,"y":0.75},{"x":0.80,"y":0.85}]] },
    { "id": "letter_e",  "kind": "letter",   "symbol": "Е", "strokes": [[{"x":0.30,"y":0.15},{"x":0.30,"y":0.85}],[{"x":0.30,"y":0.15},{"x":0.75,"y":0.15}],[{"x":0.30,"y":0.50},{"x":0.65,"y":0.50}],[{"x":0.30,"y":0.85},{"x":0.75,"y":0.85}]] },
    { "id": "letter_yo", "kind": "letter",   "symbol": "Ё", "strokes": [[{"x":0.30,"y":0.20},{"x":0.30,"y":0.85}],[{"x":0.30,"y":0.20},{"x":0.75,"y":0.20}],[{"x":0.30,"y":0.50},{"x":0.65,"y":0.50}],[{"x":0.30,"y":0.85},{"x":0.75,"y":0.85}]] },
    { "id": "letter_zh", "kind": "letter",   "symbol": "Ж", "strokes": [[{"x":0.50,"y":0.15},{"x":0.50,"y":0.85}],[{"x":0.20,"y":0.20},{"x":0.50,"y":0.50}],[{"x":0.50,"y":0.50},{"x":0.80,"y":0.20}],[{"x":0.20,"y":0.80},{"x":0.50,"y":0.50}],[{"x":0.50,"y":0.50},{"x":0.80,"y":0.80}]] },
    { "id": "letter_z",  "kind": "letter",   "symbol": "З", "strokes": [[{"x":0.30,"y":0.20},{"x":0.55,"y":0.15},{"x":0.75,"y":0.30},{"x":0.55,"y":0.45},{"x":0.45,"y":0.50}],[{"x":0.45,"y":0.50},{"x":0.65,"y":0.55},{"x":0.80,"y":0.70},{"x":0.55,"y":0.85},{"x":0.30,"y":0.80}]] },
    { "id": "letter_i",  "kind": "letter",   "symbol": "И", "strokes": [[{"x":0.30,"y":0.15},{"x":0.30,"y":0.85}],[{"x":0.30,"y":0.85},{"x":0.75,"y":0.15}],[{"x":0.75,"y":0.15},{"x":0.75,"y":0.85}]] },
    { "id": "letter_iy", "kind": "letter",   "symbol": "Й", "strokes": [[{"x":0.30,"y":0.20},{"x":0.30,"y":0.85}],[{"x":0.30,"y":0.85},{"x":0.75,"y":0.20}],[{"x":0.75,"y":0.20},{"x":0.75,"y":0.85}],[{"x":0.40,"y":0.08},{"x":0.65,"y":0.08}]] },
    { "id": "letter_k",  "kind": "letter",   "symbol": "К", "strokes": [[{"x":0.30,"y":0.15},{"x":0.30,"y":0.85}],[{"x":0.30,"y":0.50},{"x":0.75,"y":0.15}],[{"x":0.30,"y":0.50},{"x":0.75,"y":0.85}]] },
    { "id": "letter_l",  "kind": "letter",   "symbol": "Л", "strokes": [[{"x":0.20,"y":0.85},{"x":0.25,"y":0.45},{"x":0.35,"y":0.15},{"x":0.50,"y":0.15}],[{"x":0.50,"y":0.15},{"x":0.50,"y":0.85}]] },
    { "id": "letter_m",  "kind": "letter",   "symbol": "М", "strokes": [[{"x":0.20,"y":0.85},{"x":0.20,"y":0.15}],[{"x":0.20,"y":0.15},{"x":0.50,"y":0.55}],[{"x":0.50,"y":0.55},{"x":0.80,"y":0.15}],[{"x":0.80,"y":0.15},{"x":0.80,"y":0.85}]] },
    { "id": "letter_n",  "kind": "letter",   "symbol": "Н", "strokes": [[{"x":0.25,"y":0.15},{"x":0.25,"y":0.85}],[{"x":0.25,"y":0.50},{"x":0.75,"y":0.50}],[{"x":0.75,"y":0.15},{"x":0.75,"y":0.85}]] },
    { "id": "letter_o",  "kind": "letter",   "symbol": "О", "strokes": [[{"x":0.50,"y":0.15},{"x":0.25,"y":0.30},{"x":0.20,"y":0.50},{"x":0.25,"y":0.70},{"x":0.50,"y":0.85},{"x":0.75,"y":0.70},{"x":0.80,"y":0.50},{"x":0.75,"y":0.30},{"x":0.50,"y":0.15}]] },
    { "id": "letter_p",  "kind": "letter",   "symbol": "П", "strokes": [[{"x":0.25,"y":0.85},{"x":0.25,"y":0.15}],[{"x":0.25,"y":0.15},{"x":0.75,"y":0.15}],[{"x":0.75,"y":0.15},{"x":0.75,"y":0.85}]] },
    { "id": "letter_r",  "kind": "letter",   "symbol": "Р", "strokes": [[{"x":0.30,"y":0.15},{"x":0.30,"y":0.85}],[{"x":0.30,"y":0.15},{"x":0.65,"y":0.15},{"x":0.75,"y":0.25},{"x":0.75,"y":0.40},{"x":0.65,"y":0.50},{"x":0.30,"y":0.50}]] },
    { "id": "letter_s",  "kind": "letter",   "symbol": "С", "strokes": [[{"x":0.75,"y":0.25},{"x":0.55,"y":0.15},{"x":0.30,"y":0.25},{"x":0.20,"y":0.50},{"x":0.30,"y":0.75},{"x":0.55,"y":0.85},{"x":0.75,"y":0.75}]] },
    { "id": "letter_t",  "kind": "letter",   "symbol": "Т", "strokes": [[{"x":0.20,"y":0.15},{"x":0.80,"y":0.15}],[{"x":0.50,"y":0.15},{"x":0.50,"y":0.85}]] },
    { "id": "letter_u",  "kind": "letter",   "symbol": "У", "strokes": [[{"x":0.25,"y":0.15},{"x":0.50,"y":0.55}],[{"x":0.75,"y":0.15},{"x":0.50,"y":0.55},{"x":0.40,"y":0.80},{"x":0.30,"y":0.85}]] },
    { "id": "letter_f",  "kind": "letter",   "symbol": "Ф", "strokes": [[{"x":0.50,"y":0.10},{"x":0.50,"y":0.85}],[{"x":0.50,"y":0.25},{"x":0.30,"y":0.30},{"x":0.20,"y":0.45},{"x":0.30,"y":0.60},{"x":0.50,"y":0.60}],[{"x":0.50,"y":0.25},{"x":0.70,"y":0.30},{"x":0.80,"y":0.45},{"x":0.70,"y":0.60},{"x":0.50,"y":0.60}]] },
    { "id": "letter_kh", "kind": "letter",   "symbol": "Х", "strokes": [[{"x":0.20,"y":0.15},{"x":0.80,"y":0.85}],[{"x":0.80,"y":0.15},{"x":0.20,"y":0.85}]] },
    { "id": "letter_ts", "kind": "letter",   "symbol": "Ц", "strokes": [[{"x":0.25,"y":0.15},{"x":0.25,"y":0.80},{"x":0.75,"y":0.80},{"x":0.75,"y":0.15}],[{"x":0.75,"y":0.80},{"x":0.80,"y":0.95}]] },
    { "id": "letter_ch", "kind": "letter",   "symbol": "Ч", "strokes": [[{"x":0.30,"y":0.15},{"x":0.30,"y":0.45},{"x":0.45,"y":0.55},{"x":0.75,"y":0.55}],[{"x":0.75,"y":0.15},{"x":0.75,"y":0.85}]] },
    { "id": "letter_sh", "kind": "letter",   "symbol": "Ш", "strokes": [[{"x":0.20,"y":0.15},{"x":0.20,"y":0.85},{"x":0.80,"y":0.85},{"x":0.80,"y":0.15}],[{"x":0.50,"y":0.30},{"x":0.50,"y":0.85}]] },
    { "id": "letter_shch","kind":"letter",   "symbol": "Щ", "strokes": [[{"x":0.20,"y":0.15},{"x":0.20,"y":0.85},{"x":0.80,"y":0.85},{"x":0.80,"y":0.15}],[{"x":0.50,"y":0.30},{"x":0.50,"y":0.85}],[{"x":0.80,"y":0.85},{"x":0.85,"y":0.95}]] },
    { "id": "letter_hardsign","kind":"letter","symbol":"Ъ", "strokes": [[{"x":0.20,"y":0.15},{"x":0.50,"y":0.15}],[{"x":0.40,"y":0.15},{"x":0.40,"y":0.85}],[{"x":0.40,"y":0.45},{"x":0.65,"y":0.45},{"x":0.75,"y":0.55},{"x":0.75,"y":0.75},{"x":0.65,"y":0.85},{"x":0.40,"y":0.85}]] },
    { "id": "letter_y",  "kind": "letter",   "symbol": "Ы", "strokes": [[{"x":0.20,"y":0.15},{"x":0.20,"y":0.85}],[{"x":0.20,"y":0.45},{"x":0.40,"y":0.45},{"x":0.50,"y":0.55},{"x":0.50,"y":0.75},{"x":0.40,"y":0.85},{"x":0.20,"y":0.85}],[{"x":0.75,"y":0.15},{"x":0.75,"y":0.85}]] },
    { "id": "letter_softsign","kind":"letter","symbol":"Ь", "strokes": [[{"x":0.30,"y":0.15},{"x":0.30,"y":0.85}],[{"x":0.30,"y":0.45},{"x":0.55,"y":0.45},{"x":0.65,"y":0.55},{"x":0.65,"y":0.75},{"x":0.55,"y":0.85},{"x":0.30,"y":0.85}]] },
    { "id": "letter_e2", "kind": "letter",   "symbol": "Э", "strokes": [[{"x":0.25,"y":0.20},{"x":0.50,"y":0.15},{"x":0.75,"y":0.30},{"x":0.80,"y":0.50},{"x":0.75,"y":0.70},{"x":0.50,"y":0.85},{"x":0.25,"y":0.80}],[{"x":0.45,"y":0.50},{"x":0.70,"y":0.50}]] },
    { "id": "letter_yu", "kind": "letter",   "symbol": "Ю", "strokes": [[{"x":0.25,"y":0.15},{"x":0.25,"y":0.85}],[{"x":0.25,"y":0.50},{"x":0.45,"y":0.50}],[{"x":0.60,"y":0.15},{"x":0.45,"y":0.30},{"x":0.40,"y":0.50},{"x":0.45,"y":0.70},{"x":0.60,"y":0.85},{"x":0.75,"y":0.70},{"x":0.80,"y":0.50},{"x":0.75,"y":0.30},{"x":0.60,"y":0.15}]] },
    { "id": "letter_ya", "kind": "letter",   "symbol": "Я", "strokes": [[{"x":0.75,"y":0.85},{"x":0.75,"y":0.15}],[{"x":0.75,"y":0.15},{"x":0.40,"y":0.15},{"x":0.30,"y":0.25},{"x":0.30,"y":0.40},{"x":0.40,"y":0.50},{"x":0.75,"y":0.50}],[{"x":0.40,"y":0.50},{"x":0.25,"y":0.85}]] },
    { "id": "syll_sha",  "kind": "syllable", "symbol": "ША", "strokes": [[{"x":0.10,"y":0.15},{"x":0.10,"y":0.85},{"x":0.40,"y":0.85},{"x":0.40,"y":0.15}],[{"x":0.25,"y":0.30},{"x":0.25,"y":0.85}],[{"x":0.55,"y":0.85},{"x":0.70,"y":0.15},{"x":0.85,"y":0.85}],[{"x":0.62,"y":0.55},{"x":0.78,"y":0.55}]] },
    { "id": "syll_ra",   "kind": "syllable", "symbol": "РА", "strokes": [[{"x":0.10,"y":0.15},{"x":0.10,"y":0.85}],[{"x":0.10,"y":0.15},{"x":0.35,"y":0.15},{"x":0.45,"y":0.25},{"x":0.45,"y":0.40},{"x":0.35,"y":0.50},{"x":0.10,"y":0.50}],[{"x":0.55,"y":0.85},{"x":0.70,"y":0.15},{"x":0.85,"y":0.85}],[{"x":0.62,"y":0.55},{"x":0.78,"y":0.55}]] },
    { "id": "syll_lo",   "kind": "syllable", "symbol": "ЛО", "strokes": [[{"x":0.05,"y":0.85},{"x":0.12,"y":0.45},{"x":0.20,"y":0.15},{"x":0.32,"y":0.15}],[{"x":0.32,"y":0.15},{"x":0.32,"y":0.85}],[{"x":0.70,"y":0.15},{"x":0.55,"y":0.30},{"x":0.50,"y":0.50},{"x":0.55,"y":0.70},{"x":0.70,"y":0.85},{"x":0.85,"y":0.70},{"x":0.90,"y":0.50},{"x":0.85,"y":0.30},{"x":0.70,"y":0.15}]] },
    { "id": "syll_zhu",  "kind": "syllable", "symbol": "ЖУ", "strokes": [[{"x":0.25,"y":0.15},{"x":0.25,"y":0.85}],[{"x":0.08,"y":0.20},{"x":0.25,"y":0.50}],[{"x":0.25,"y":0.50},{"x":0.42,"y":0.20}],[{"x":0.08,"y":0.80},{"x":0.25,"y":0.50}],[{"x":0.25,"y":0.50},{"x":0.42,"y":0.80}],[{"x":0.55,"y":0.15},{"x":0.70,"y":0.55}],[{"x":0.85,"y":0.15},{"x":0.70,"y":0.55},{"x":0.60,"y":0.80},{"x":0.50,"y":0.85}]] },
    { "id": "syll_che",  "kind": "syllable", "symbol": "ЧЕ", "strokes": [[{"x":0.10,"y":0.15},{"x":0.10,"y":0.45},{"x":0.22,"y":0.55},{"x":0.40,"y":0.55}],[{"x":0.40,"y":0.15},{"x":0.40,"y":0.85}],[{"x":0.55,"y":0.15},{"x":0.55,"y":0.85}],[{"x":0.55,"y":0.15},{"x":0.85,"y":0.15}],[{"x":0.55,"y":0.50},{"x":0.78,"y":0.50}],[{"x":0.55,"y":0.85},{"x":0.85,"y":0.85}]] },
    { "id": "syll_shchi","kind": "syllable", "symbol": "ЩИ", "strokes": [[{"x":0.05,"y":0.15},{"x":0.05,"y":0.78},{"x":0.40,"y":0.78},{"x":0.40,"y":0.15}],[{"x":0.22,"y":0.30},{"x":0.22,"y":0.78}],[{"x":0.40,"y":0.78},{"x":0.45,"y":0.92}],[{"x":0.55,"y":0.15},{"x":0.55,"y":0.85}],[{"x":0.55,"y":0.85},{"x":0.85,"y":0.15}],[{"x":0.85,"y":0.15},{"x":0.85,"y":0.85}]] },
    { "id": "syll_so",   "kind": "syllable", "symbol": "СО", "strokes": [[{"x":0.40,"y":0.25},{"x":0.30,"y":0.15},{"x":0.15,"y":0.25},{"x":0.10,"y":0.50},{"x":0.15,"y":0.75},{"x":0.30,"y":0.85},{"x":0.40,"y":0.75}],[{"x":0.70,"y":0.15},{"x":0.55,"y":0.30},{"x":0.50,"y":0.50},{"x":0.55,"y":0.70},{"x":0.70,"y":0.85},{"x":0.85,"y":0.70},{"x":0.90,"y":0.50},{"x":0.85,"y":0.30},{"x":0.70,"y":0.15}]] },
    { "id": "syll_tsa",  "kind": "syllable", "symbol": "ЦА", "strokes": [[{"x":0.10,"y":0.15},{"x":0.10,"y":0.78},{"x":0.40,"y":0.78},{"x":0.40,"y":0.15}],[{"x":0.40,"y":0.78},{"x":0.45,"y":0.95}],[{"x":0.55,"y":0.85},{"x":0.70,"y":0.15},{"x":0.85,"y":0.85}],[{"x":0.62,"y":0.55},{"x":0.78,"y":0.55}]] },
    { "id": "syll_zo",   "kind": "syllable", "symbol": "ЗО", "strokes": [[{"x":0.10,"y":0.20},{"x":0.25,"y":0.15},{"x":0.40,"y":0.30},{"x":0.25,"y":0.45},{"x":0.20,"y":0.50}],[{"x":0.20,"y":0.50},{"x":0.30,"y":0.55},{"x":0.42,"y":0.70},{"x":0.25,"y":0.85},{"x":0.10,"y":0.80}],[{"x":0.70,"y":0.15},{"x":0.55,"y":0.30},{"x":0.50,"y":0.50},{"x":0.55,"y":0.70},{"x":0.70,"y":0.85},{"x":0.85,"y":0.70},{"x":0.90,"y":0.50},{"x":0.85,"y":0.30},{"x":0.70,"y":0.15}]] },
    { "id": "syll_li",   "kind": "syllable", "symbol": "ЛИ", "strokes": [[{"x":0.05,"y":0.85},{"x":0.12,"y":0.45},{"x":0.20,"y":0.15},{"x":0.32,"y":0.15}],[{"x":0.32,"y":0.15},{"x":0.32,"y":0.85}],[{"x":0.55,"y":0.15},{"x":0.55,"y":0.85}],[{"x":0.55,"y":0.85},{"x":0.85,"y":0.15}],[{"x":0.85,"y":0.15},{"x":0.85,"y":0.85}]] }
  ]
}
