{
  "id": "pack_lexical_v1",
  "soundTarget": "lexical",
  "group": "лексика",
  "version": 1,
  "description": "Лексические и грамматические упражнения по темам детского словаря 5–8 лет. Развитие словарного запаса, антонимов, синонимов, обобщений, словоизменения.",
  "stages": {
    "animals_wild": {
      "stageId": "animals_wild",
      "note": "Дикие животные — лексическая тема.",
      "items": [
        { "id": "lex-aw-0",  "word": "лиса",          "hint": "Лиса рыжая и хитрая. Живёт в лесу.", "difficulty": 1 },
        { "id": "lex-aw-1",  "word": "волк",          "hint": "Волк серый и сильный. Воет на луну.", "difficulty": 1 },
        { "id": "lex-aw-2",  "word": "медведь",       "hint": "Медведь большой и бурый. Спит зимой.", "difficulty": 1 },
        { "id": "lex-aw-3",  "word": "заяц",          "hint": "Заяц белый зимой, серый летом. Быстро бегает.", "difficulty": 1 },
        { "id": "lex-aw-4",  "word": "ёж",            "hint": "Ёж колючий. Несёт грибы и яблоки.", "difficulty": 1 },
        { "id": "lex-aw-5",  "word": "белка",         "hint": "Белка рыжая. Прыгает по деревьям и собирает орехи.", "difficulty": 1 },
        { "id": "lex-aw-6",  "word": "олень",         "hint": "У оленя рога. Он живёт в лесу.", "difficulty": 2 },
        { "id": "lex-aw-7",  "word": "кабан",         "hint": "Кабан — дикая свинья с клыками.", "difficulty": 2 },
        { "id": "lex-aw-8",  "word": "лось",          "hint": "Лось большой с широкими рогами.", "difficulty": 2 },
        { "id": "lex-aw-9",  "word": "рысь",          "hint": "Рысь — дикая кошка с кисточками на ушах.", "difficulty": 3 },
        { "id": "lex-aw-10", "word": "обобщение: дикие животные", "hint": "Лиса, волк, медведь, заяц — все ДИКИЕ ЖИВОТНЫЕ.", "difficulty": 2 },
        { "id": "lex-aw-11", "word": "кто лишний: кошка, волк, лиса, заяц?", "hint": "Кошка — домашнее. Волк, лиса, заяц — дикие. Кошка лишняя!", "difficulty": 3 },
        { "id": "lex-aw-12", "word": "чьи детёныши: лиса — ...", "hint": "Лиса — лисёнок. Медведь — медвежонок. Заяц — зайчонок.", "difficulty": 3 },
        { "id": "lex-aw-13", "word": "кто что ест? Волк — ...", "hint": "Волк — мясо. Заяц — морковь. Медведь — мёд и рыбу.", "difficulty": 3 },
        { "id": "lex-aw-14", "word": "где живут: лиса — ...", "hint": "Лиса — в норе. Медведь — в берлоге. Белка — в дупле.", "difficulty": 3 }
      ]
    },
    "animals_domestic": {
      "stageId": "animals_domestic",
      "note": "Домашние животные — лексическая тема.",
      "items": [
        { "id": "lex-ad-0",  "word": "кошка",         "hint": "Кошка мурлычет. Ловит мышей.", "difficulty": 1 },
        { "id": "lex-ad-1",  "word": "собака",        "hint": "Собака лает и охраняет дом.", "difficulty": 1 },
        { "id": "lex-ad-2",  "word": "корова",        "hint": "Корова мычит. Даёт молоко.", "difficulty": 1 },
        { "id": "lex-ad-3",  "word": "лошадь",        "hint": "Лошадь ржёт. Люди на ней ездят.", "difficulty": 1 },
        { "id": "lex-ad-4",  "word": "свинья",        "hint": "Свинья хрюкает. Живёт в хлеву.", "difficulty": 1 },
        { "id": "lex-ad-5",  "word": "курица",        "hint": "Курица кудахчет. Несёт яйца.", "difficulty": 1 },
        { "id": "lex-ad-6",  "word": "кролик",        "hint": "Кролик грызёт морковь.", "difficulty": 2 },
        { "id": "lex-ad-7",  "word": "козёл",         "hint": "Козёл с рогами. Блеет: ме-е-е!", "difficulty": 2 },
        { "id": "lex-ad-8",  "word": "овца",          "hint": "Овца даёт шерсть для тёплой одежды.", "difficulty": 2 },
        { "id": "lex-ad-9",  "word": "утка",          "hint": "Утка крякает. Плавает в пруду.", "difficulty": 1 },
        { "id": "lex-ad-10", "word": "обобщение: домашние животные", "hint": "Кошка, собака, корова — ДОМАШНИЕ ЖИВОТНЫЕ. Живут рядом с людьми.", "difficulty": 2 },
        { "id": "lex-ad-11", "word": "кто лишний: волк, кошка, собака?", "hint": "Волк — дикий! Кошка и собака — домашние. Волк лишний!", "difficulty": 3 },
        { "id": "lex-ad-12", "word": "детёныши: кошка — ...", "hint": "Кошка — котёнок. Собака — щенок. Корова — телёнок.", "difficulty": 3 },
        { "id": "lex-ad-13", "word": "что даёт корова?",    "hint": "Молоко, мясо, кожу. Из молока делают масло и сыр.", "difficulty": 3 },
        { "id": "lex-ad-14", "word": "польза домашних животных", "hint": "Корова — молоко. Курица — яйца. Овца — шерсть. Лошадь — перевозки.", "difficulty": 3 }
      ]
    },
    "birds": {
      "stageId": "birds",
      "note": "Птицы — лексическая тема.",
      "items": [
        { "id": "lex-bi-0",  "word": "воробей",       "hint": "Маленькая птичка. Чирикает: чик-чирик!", "difficulty": 1 },
        { "id": "lex-bi-1",  "word": "ворона",        "hint": "Ворона большая и серая. Кар-кар!", "difficulty": 1 },
        { "id": "lex-bi-2",  "word": "голубь",        "hint": "Голубь воркует. Живёт в городе.", "difficulty": 1 },
        { "id": "lex-bi-3",  "word": "ласточка",      "hint": "Ласточка стрела! Прилетает весной.", "difficulty": 2 },
        { "id": "lex-bi-4",  "word": "соловей",       "hint": "Соловей красиво поёт ночью.", "difficulty": 2 },
        { "id": "lex-bi-5",  "word": "дятел",         "hint": "Дятел стучит по дереву: тук-тук-тук!", "difficulty": 2 },
        { "id": "lex-bi-6",  "word": "сова",          "hint": "Сова охотится ночью. Ух-ух!", "difficulty": 2 },
        { "id": "lex-bi-7",  "word": "орёл",          "hint": "Орёл большой и сильный. Парит высоко.", "difficulty": 2 },
        { "id": "lex-bi-8",  "word": "пингвин",       "hint": "Пингвин не летает. Живёт на льду.", "difficulty": 2 },
        { "id": "lex-bi-9",  "word": "страус",        "hint": "Страус большой. Бегает, не летает.", "difficulty": 2 },
        { "id": "lex-bi-10", "word": "перелётные птицы", "hint": "Ласточка, соловей, аист улетают на юг зимой.", "difficulty": 3 },
        { "id": "lex-bi-11", "word": "зимующие птицы",   "hint": "Воробей, ворона, синица остаются зимой.", "difficulty": 3 },
        { "id": "lex-bi-12", "word": "части тела птицы",  "hint": "Крылья, хвост, клюв, перья, лапки.", "difficulty": 3 },
        { "id": "lex-bi-13", "word": "что делает птица?", "hint": "Летает, поёт, клюёт, вьёт гнездо, высиживает яйца.", "difficulty": 3 },
        { "id": "lex-bi-14", "word": "кто лишний: орёл, ворона, рыба, голубь?", "hint": "Рыба — не птица! Она плавает. Лишняя!", "difficulty": 2 }
      ]
    },
    "vegetables_fruits": {
      "stageId": "vegetables_fruits",
      "note": "Овощи и фрукты — лексическая тема.",
      "items": [
        { "id": "lex-vf-0",  "word": "яблоко",        "hint": "Яблоко круглое, красное или зелёное. Растёт на дереве.", "difficulty": 1 },
        { "id": "lex-vf-1",  "word": "груша",         "hint": "Груша жёлтая. Растёт на дереве.", "difficulty": 1 },
        { "id": "lex-vf-2",  "word": "банан",         "hint": "Банан жёлтый и длинный. Привозят из жарких стран.", "difficulty": 1 },
        { "id": "lex-vf-3",  "word": "апельсин",      "hint": "Апельсин круглый и оранжевый. Кислый и сладкий.", "difficulty": 2 },
        { "id": "lex-vf-4",  "word": "морковь",       "hint": "Морковь оранжевая. Растёт в земле.", "difficulty": 1 },
        { "id": "lex-vf-5",  "word": "картошка",      "hint": "Картошка растёт в земле. Варят, жарят.", "difficulty": 1 },
        { "id": "lex-vf-6",  "word": "капуста",       "hint": "Капуста зелёная. Из неё делают щи.", "difficulty": 1 },
        { "id": "lex-vf-7",  "word": "помидор",       "hint": "Помидор красный и круглый. Растёт в огороде.", "difficulty": 2 },
        { "id": "lex-vf-8",  "word": "огурец",        "hint": "Огурец зелёный и длинный. Растёт в огороде.", "difficulty": 2 },
        { "id": "lex-vf-9",  "word": "лук",           "hint": "Лук горький. От него щиплет глаза.", "difficulty": 1 },
        { "id": "lex-vf-10", "word": "обобщение: фрукты", "hint": "Яблоко, груша, банан — ФРУКТЫ. Растут на деревьях.", "difficulty": 2 },
        { "id": "lex-vf-11", "word": "обобщение: овощи",  "hint": "Морковь, картошка, капуста — ОВОЩИ. Растут в огороде.", "difficulty": 2 },
        { "id": "lex-vf-12", "word": "кто лишний: яблоко, морковь, груша, банан?", "hint": "Морковь — овощ! Яблоко, груша, банан — фрукты. Морковь лишняя!", "difficulty": 3 },
        { "id": "lex-vf-13", "word": "какой вкус: лимон?", "hint": "Лимон кислый. Сахар сладкий. Перец острый. Соль солёная.", "difficulty": 2 },
        { "id": "lex-vf-14", "word": "что можно приготовить из яблока?", "hint": "Сок, варенье, пирог, компот, пюре!", "difficulty": 3 }
      ]
    },
    "clothing": {
      "stageId": "clothing",
      "note": "Одежда — лексическая тема.",
      "items": [
        { "id": "lex-cl-0",  "word": "рубашка",       "hint": "Рубашка — одежда для туловища.", "difficulty": 1 },
        { "id": "lex-cl-1",  "word": "брюки",         "hint": "Брюки — одежда для ног.", "difficulty": 1 },
        { "id": "lex-cl-2",  "word": "платье",        "hint": "Платье носят девочки.", "difficulty": 1 },
        { "id": "lex-cl-3",  "word": "куртка",        "hint": "Куртку надевают осенью и весной.", "difficulty": 1 },
        { "id": "lex-cl-4",  "word": "шапка",         "hint": "Шапку надевают зимой.", "difficulty": 1 },
        { "id": "lex-cl-5",  "word": "сапоги",        "hint": "Сапоги надевают в дождь.", "difficulty": 1 },
        { "id": "lex-cl-6",  "word": "шуба",          "hint": "Шуба из меха. Очень тёплая.", "difficulty": 2 },
        { "id": "lex-cl-7",  "word": "носки",         "hint": "Носки надевают под обувь.", "difficulty": 1 },
        { "id": "lex-cl-8",  "word": "свитер",        "hint": "Свитер вязаный и тёплый.", "difficulty": 2 },
        { "id": "lex-cl-9",  "word": "перчатки",      "hint": "Перчатки надевают на руки зимой.", "difficulty": 2 },
        { "id": "lex-cl-10", "word": "обобщение: одежда", "hint": "Рубашка, платье, куртка — всё это ОДЕЖДА.", "difficulty": 2 },
        { "id": "lex-cl-11", "word": "зимняя одежда: назови", "hint": "Шуба, шапка, шарф, перчатки, сапоги.", "difficulty": 2 },
        { "id": "lex-cl-12", "word": "летняя одежда: назови", "hint": "Платье, шорты, майка, сандалии.", "difficulty": 2 },
        { "id": "lex-cl-13", "word": "что из чего: шапка из шерсти", "hint": "Шапка — из шерсти. Сапоги — из кожи. Куртка — из ткани.", "difficulty": 3 },
        { "id": "lex-cl-14", "word": "надену — сниму: глаголы",  "hint": "Утром надеваю. Вечером снимаю. Надел-снял!", "difficulty": 2 }
      ]
    },
    "transport": {
      "stageId": "transport",
      "note": "Транспорт — лексическая тема.",
      "items": [
        { "id": "lex-tr-0",  "word": "машина",        "hint": "Машина ездит по дороге. Бибикает!", "difficulty": 1 },
        { "id": "lex-tr-1",  "word": "автобус",       "hint": "Автобус большой. Везёт много людей.", "difficulty": 1 },
        { "id": "lex-tr-2",  "word": "самолёт",       "hint": "Самолёт летит по небу.", "difficulty": 1 },
        { "id": "lex-tr-3",  "word": "корабль",       "hint": "Корабль плывёт по морю.", "difficulty": 1 },
        { "id": "lex-tr-4",  "word": "поезд",         "hint": "Поезд едет по рельсам. Ту-ту!", "difficulty": 1 },
        { "id": "lex-tr-5",  "word": "велосипед",     "hint": "На велосипеде крутишь педали.", "difficulty": 2 },
        { "id": "lex-tr-6",  "word": "вертолёт",      "hint": "Вертолёт летит с пропеллером вверху.", "difficulty": 2 },
        { "id": "lex-tr-7",  "word": "трамвай",       "hint": "Трамвай ездит по рельсам в городе.", "difficulty": 2 },
        { "id": "lex-tr-8",  "word": "метро",         "hint": "Метро едет под землёй.", "difficulty": 2 },
        { "id": "lex-tr-9",  "word": "грузовик",      "hint": "Грузовик перевозит грузы — тяжёлые вещи.", "difficulty": 2 },
        { "id": "lex-tr-10", "word": "обобщение: транспорт", "hint": "Машина, самолёт, корабль — всё это ТРАНСПОРТ.", "difficulty": 2 },
        { "id": "lex-tr-11", "word": "воздушный транспорт", "hint": "Самолёт, вертолёт, воздушный шар.", "difficulty": 3 },
        { "id": "lex-tr-12", "word": "водный транспорт",    "hint": "Корабль, лодка, катер, подводная лодка.", "difficulty": 3 },
        { "id": "lex-tr-13", "word": "наземный транспорт",  "hint": "Машина, автобус, поезд, велосипед.", "difficulty": 3 },
        { "id": "lex-tr-14", "word": "кто управляет?",      "hint": "Машиной — водитель. Самолётом — пилот. Кораблём — капитан.", "difficulty": 3 }
      ]
    },
    "body_parts": {
      "stageId": "body_parts",
      "note": "Части тела — лексическая тема.",
      "items": [
        { "id": "lex-bp-0",  "word": "голова",        "hint": "Голова вверху. В ней мозг.", "difficulty": 1 },
        { "id": "lex-bp-1",  "word": "глаза",         "hint": "Глаза — видят. Два глаза.", "difficulty": 1 },
        { "id": "lex-bp-2",  "word": "уши",           "hint": "Уши — слышат. Два уха.", "difficulty": 1 },
        { "id": "lex-bp-3",  "word": "нос",           "hint": "Нос — нюхает и дышит.", "difficulty": 1 },
        { "id": "lex-bp-4",  "word": "рот",           "hint": "Рот — говорит и ест.", "difficulty": 1 },
        { "id": "lex-bp-5",  "word": "руки",          "hint": "Руки — берут и делают. Две руки.", "difficulty": 1 },
        { "id": "lex-bp-6",  "word": "ноги",          "hint": "Ноги — ходят и бегают. Две ноги.", "difficulty": 1 },
        { "id": "lex-bp-7",  "word": "пальцы",        "hint": "На руках 10 пальцев, на ногах тоже.", "difficulty": 2 },
        { "id": "lex-bp-8",  "word": "спина",         "hint": "Спина сзади. Прямая спина — это здорово!", "difficulty": 2 },
        { "id": "lex-bp-9",  "word": "живот",         "hint": "Живот спереди. Там желудок.", "difficulty": 1 },
        { "id": "lex-bp-10", "word": "для чего нос?",  "hint": "Нос нюхает цветы, дышит, чувствует запах.", "difficulty": 2 },
        { "id": "lex-bp-11", "word": "для чего уши?",  "hint": "Уши слышат музыку, голоса, звуки.", "difficulty": 2 },
        { "id": "lex-bp-12", "word": "моя-мой-моё: рот, нос, ухо", "hint": "Мой нос. Моё ухо. Мой рот. Мои глаза.", "difficulty": 2 },
        { "id": "lex-bp-13", "word": "единственное-множественное", "hint": "Один глаз — два глаза. Одно ухо — два уха. Один рот — нет мн.ч!", "difficulty": 3 },
        { "id": "lex-bp-14", "word": "болит: живот, голова, горло", "hint": "У меня болит живот. У меня болит голова. У меня болит горло.", "difficulty": 3 }
      ]
    },
    "colors_shapes": {
      "stageId": "colors_shapes",
      "note": "Цвета и формы — лексическая тема.",
      "items": [
        { "id": "lex-cs-0",  "word": "красный",       "hint": "Красный — как яблоко, помидор, роза.", "difficulty": 1 },
        { "id": "lex-cs-1",  "word": "синий",         "hint": "Синий — как небо и море.", "difficulty": 1 },
        { "id": "lex-cs-2",  "word": "жёлтый",        "hint": "Жёлтый — как солнце и банан.", "difficulty": 1 },
        { "id": "lex-cs-3",  "word": "зелёный",       "hint": "Зелёный — как трава и листья.", "difficulty": 1 },
        { "id": "lex-cs-4",  "word": "оранжевый",     "hint": "Оранжевый — как апельсин и морковь.", "difficulty": 2 },
        { "id": "lex-cs-5",  "word": "фиолетовый",    "hint": "Фиолетовый — как фиалка и баклажан.", "difficulty": 2 },
        { "id": "lex-cs-6",  "word": "квадрат",       "hint": "Квадрат — четыре равных стороны.", "difficulty": 1 },
        { "id": "lex-cs-7",  "word": "круг",          "hint": "Круг — нет углов, как колесо.", "difficulty": 1 },
        { "id": "lex-cs-8",  "word": "треугольник",   "hint": "Треугольник — три стороны и три угла.", "difficulty": 2 },
        { "id": "lex-cs-9",  "word": "прямоугольник", "hint": "Прямоугольник — как книга или дверь.", "difficulty": 2 },
        { "id": "lex-cs-10", "word": "какой формы: яблоко?", "hint": "Яблоко круглое. Огурец длинный. Пирожок — овальный.", "difficulty": 2 },
        { "id": "lex-cs-11", "word": "какого цвета: трава?",  "hint": "Трава зелёная. Снег белый. Уголь чёрный.", "difficulty": 1 },
        { "id": "lex-cs-12", "word": "подбери прилагательное к существительному", "hint": "Красное яблоко. Синее небо. Зелёная трава.", "difficulty": 3 },
        { "id": "lex-cs-13", "word": "смешивание цветов: синий + жёлтый = ?", "hint": "Синий + жёлтый = зелёный! Красный + синий = фиолетовый!", "difficulty": 3 },
        { "id": "lex-cs-14", "word": "тёплые и холодные цвета", "hint": "Тёплые: красный, оранжевый, жёлтый. Холодные: синий, голубой, зелёный.", "difficulty": 3 }
      ]
    },
    "antonyms": {
      "stageId": "antonyms",
      "note": "Антонимы — слова с противоположным значением.",
      "items": [
        { "id": "lex-an-0",  "word": "большой — маленький",   "hint": "Большой слон — маленький мышонок.", "difficulty": 1 },
        { "id": "lex-an-1",  "word": "высокий — низкий",      "hint": "Высокая башня — низкий забор.", "difficulty": 1 },
        { "id": "lex-an-2",  "word": "длинный — короткий",    "hint": "Длинный шарф — короткий носок.", "difficulty": 1 },
        { "id": "lex-an-3",  "word": "быстрый — медленный",   "hint": "Быстрый зайчик — медленная черепаха.", "difficulty": 2 },
        { "id": "lex-an-4",  "word": "горячий — холодный",    "hint": "Горячий чай — холодный лёд.", "difficulty": 1 },
        { "id": "lex-an-5",  "word": "светлый — тёмный",      "hint": "Светлый день — тёмная ночь.", "difficulty": 2 },
        { "id": "lex-an-6",  "word": "добрый — злой",         "hint": "Добрая фея — злой волшебник.", "difficulty": 2 },
        { "id": "lex-an-7",  "word": "новый — старый",        "hint": "Новая игрушка — старая шапка.", "difficulty": 2 },
        { "id": "lex-an-8",  "word": "лёгкий — тяжёлый",      "hint": "Лёгкое перо — тяжёлый камень.", "difficulty": 2 },
        { "id": "lex-an-9",  "word": "тихий — громкий",       "hint": "Тихий шёпот — громкий крик.", "difficulty": 2 },
        { "id": "lex-an-10", "word": "мокрый — сухой",        "hint": "Мокрый зонт — сухой полотенце.", "difficulty": 2 },
        { "id": "lex-an-11", "word": "весёлый — грустный",    "hint": "Весёлый клоун — грустный мишка.", "difficulty": 2 },
        { "id": "lex-an-12", "word": "вверх — вниз",          "hint": "Самолёт летит вверх. Мяч упал вниз.", "difficulty": 2 },
        { "id": "lex-an-13", "word": "начало — конец",        "hint": "Начало сказки — конец сказки.", "difficulty": 2 },
        { "id": "lex-an-14", "word": "любить — ненавидеть",   "hint": "Я люблю мороженое. Я не люблю горькое.", "difficulty": 3 }
      ]
    },
    "verbs": {
      "stageId": "verbs",
      "note": "Глаголы — действия предметов и живых существ.",
      "items": [
        { "id": "lex-vb-0",  "word": "кошка — мяукает, мурлычет",   "hint": "Кошка мяукает и мурлычет.", "difficulty": 1 },
        { "id": "lex-vb-1",  "word": "собака — лает, рычит",         "hint": "Собака лает и рычит.", "difficulty": 1 },
        { "id": "lex-vb-2",  "word": "птица — поёт, летит",          "hint": "Птица поёт и летит.", "difficulty": 1 },
        { "id": "lex-vb-3",  "word": "рыба — плывёт, ныряет",        "hint": "Рыба плывёт и ныряет.", "difficulty": 1 },
        { "id": "lex-vb-4",  "word": "ребёнок — играет, бежит",      "hint": "Ребёнок играет, бежит, прыгает, смеётся.", "difficulty": 2 },
        { "id": "lex-vb-5",  "word": "что делает повар?",            "hint": "Повар варит, жарит, режет, пробует.", "difficulty": 2 },
        { "id": "lex-vb-6",  "word": "что делает врач?",             "hint": "Врач лечит, осматривает, слушает, прописывает.", "difficulty": 2 },
        { "id": "lex-vb-7",  "word": "что делает учитель?",          "hint": "Учитель учит, объясняет, проверяет, задаёт.", "difficulty": 2 },
        { "id": "lex-vb-8",  "word": "один действует: я иду",        "hint": "Я иду. Ты идёшь. Он идёт. Мы идём.", "difficulty": 3 },
        { "id": "lex-vb-9",  "word": "прошедшее время: шёл, бежал",  "hint": "Я шёл — я шла (по-разному для мальчика и девочки!).", "difficulty": 3 },
        { "id": "lex-vb-10", "word": "антонимы-глаголы: открыл — закрыл", "hint": "Открыл дверь — закрыл дверь. Встал — сел.", "difficulty": 3 },
        { "id": "lex-vb-11", "word": "подбери действие: снег — падает, идёт, кружится", "hint": "Снег падает, идёт, кружится, тает.", "difficulty": 3 },
        { "id": "lex-vb-12", "word": "подбери действие: солнце — ...", "hint": "Солнце светит, греет, восходит, заходит.", "difficulty": 3 },
        { "id": "lex-vb-13", "word": "подбери действие: ветер — ...", "hint": "Ветер дует, свистит, качает деревья, несёт листья.", "difficulty": 3 },
        { "id": "lex-vb-14", "word": "кто что умеет: лягушка прыгает", "hint": "Лягушка прыгает. Рыба плывёт. Птица летит. Змея ползёт.", "difficulty": 3 }
      ]
    },
    "grammar_cases": {
      "stageId": "grammar_cases",
      "note": "Грамматика: падежи, согласование, предлоги.",
      "items": [
        { "id": "lex-gc-0",  "word": "предлог НА: книга на столе",        "hint": "На — сверху. Книга на столе. Шапка на голове.", "difficulty": 2 },
        { "id": "lex-gc-1",  "word": "предлог В: мяч в коробке",          "hint": "В — внутри. Мяч в коробке. Карандаш в пенале.", "difficulty": 2 },
        { "id": "lex-gc-2",  "word": "предлог ПОД: кот под стулом",       "hint": "Под — снизу. Кот под стулом. Тапки под кроватью.", "difficulty": 2 },
        { "id": "lex-gc-3",  "word": "предлог ЗА: солнце за тучей",       "hint": "За — позади. Солнце за тучей. Кот за диваном.", "difficulty": 2 },
        { "id": "lex-gc-4",  "word": "предлог ПЕРЕД: стол перед окном",   "hint": "Перед — впереди. Стол перед окном.", "difficulty": 2 },
        { "id": "lex-gc-5",  "word": "один-много: кот — коты",            "hint": "Один кот — много котов. Одна лиса — много лис.", "difficulty": 2 },
        { "id": "lex-gc-6",  "word": "один-много: дерево — деревья",       "hint": "Одно дерево — много деревьев. Одно яблоко — много яблок.", "difficulty": 3 },
        { "id": "lex-gc-7",  "word": "родительный падеж: нет чего?",       "hint": "Нет кота. Нет лисы. Нет дерева. Нет яблока.", "difficulty": 3 },
        { "id": "lex-gc-8",  "word": "дательный падеж: дать кому?",        "hint": "Дать коту. Дать лисе. Дать маме. Дать другу.", "difficulty": 3 },
        { "id": "lex-gc-9",  "word": "уменьшительные: кот — котик",       "hint": "Кот — котик. Дом — домик. Лиса — лисичка. Нос — носик.", "difficulty": 2 },
        { "id": "lex-gc-10", "word": "согласование: красивый мяч",         "hint": "Красный мяч (м.р.). Красная лиса (ж.р.). Красное яблоко (ср.р.).", "difficulty": 3 },
        { "id": "lex-gc-11", "word": "согласование: два-пять",             "hint": "Два кота, три кота, пять котов. Два яблока, пять яблок.", "difficulty": 3 },
        { "id": "lex-gc-12", "word": "противоположный предлог: на → под",  "hint": "Положил НА стол — упал ПОД стол. Вошёл В дом — вышел ИЗ дома.", "difficulty": 3 },
        { "id": "lex-gc-13", "word": "куда? — где?: иду В лес — я В лесу", "hint": "Иду В лес (куда?). Нахожусь В лесу (где?).", "difficulty": 4 },
        { "id": "lex-gc-14", "word": "притяжательные: мой — моя — моё",   "hint": "Мой кот. Моя кошка. Моё яблоко. Мои игрушки.", "difficulty": 3 }
      ]
    },
    "seasons_weather": {
      "stageId": "seasons_weather",
      "note": "Времена года и погода — лексическая тема.",
      "items": [
        { "id": "lex-sw-0",  "word": "осень",         "hint": "Осенью листья желтеют, идёт дождь.", "difficulty": 1 },
        { "id": "lex-sw-1",  "word": "зима",          "hint": "Зимой холодно, идёт снег, замерзают реки.", "difficulty": 1 },
        { "id": "lex-sw-2",  "word": "весна",         "hint": "Весной тает снег, прилетают птицы.", "difficulty": 1 },
        { "id": "lex-sw-3",  "word": "лето",          "hint": "Летом жарко, купаются, едят мороженое.", "difficulty": 1 },
        { "id": "lex-sw-4",  "word": "солнечно",      "hint": "Сегодня солнечно — светит солнце!", "difficulty": 1 },
        { "id": "lex-sw-5",  "word": "облачно",       "hint": "Облачно — много облаков на небе.", "difficulty": 2 },
        { "id": "lex-sw-6",  "word": "дождливо",      "hint": "Дождливо — идёт дождь. Нужен зонт!", "difficulty": 1 },
        { "id": "lex-sw-7",  "word": "снежно",        "hint": "Снежно — идёт снег. Белым-бело!", "difficulty": 1 },
        { "id": "lex-sw-8",  "word": "ветрено",       "hint": "Ветрено — дует сильный ветер.", "difficulty": 2 },
        { "id": "lex-sw-9",  "word": "морозно",       "hint": "Морозно — очень холодно. Мороз.", "difficulty": 2 },
        { "id": "lex-sw-10", "word": "что бывает зимой?",  "hint": "Снег, мороз, лёд, метель, Новый год.", "difficulty": 2 },
        { "id": "lex-sw-11", "word": "что бывает летом?",  "hint": "Жара, дождь, радуга, гроза, купание.", "difficulty": 2 },
        { "id": "lex-sw-12", "word": "порядок месяцев",    "hint": "Декабрь-Январь-Февраль — зима. Март-Апрель-Май — весна.", "difficulty": 3 },
        { "id": "lex-sw-13", "word": "одевайся по погоде", "hint": "Дождь → зонт и резиновые сапоги. Снег → шуба и шапка.", "difficulty": 2 },
        { "id": "lex-sw-14", "word": "Какая сейчас погода?", "hint": "Скажи: «Сейчас... (тепло/холодно/солнечно)».", "difficulty": 2 }
      ]
    },
    "house_furniture": {
      "stageId": "house_furniture",
      "note": "Дом и мебель — лексическая тема.",
      "items": [
        { "id": "lex-hf-0",  "word": "стол",          "hint": "Стол — за ним едят и делают уроки.", "difficulty": 1 },
        { "id": "lex-hf-1",  "word": "стул",          "hint": "Стул — на нём сидят.", "difficulty": 1 },
        { "id": "lex-hf-2",  "word": "кровать",       "hint": "Кровать — на ней спят.", "difficulty": 1 },
        { "id": "lex-hf-3",  "word": "шкаф",          "hint": "В шкафу хранят одежду.", "difficulty": 1 },
        { "id": "lex-hf-4",  "word": "диван",         "hint": "На диване отдыхают и смотрят телевизор.", "difficulty": 1 },
        { "id": "lex-hf-5",  "word": "полка",         "hint": "На полке стоят книги и игрушки.", "difficulty": 2 },
        { "id": "lex-hf-6",  "word": "окно",          "hint": "Через окно видно улицу.", "difficulty": 1 },
        { "id": "lex-hf-7",  "word": "дверь",         "hint": "Дверь открывают и закрывают.", "difficulty": 1 },
        { "id": "lex-hf-8",  "word": "пол",           "hint": "Пол внизу, потолок вверху.", "difficulty": 1 },
        { "id": "lex-hf-9",  "word": "ковёр",         "hint": "Ковёр лежит на полу. Мягкий.", "difficulty": 2 },
        { "id": "lex-hf-10", "word": "обобщение: мебель", "hint": "Стол, стул, кровать, шкаф — всё это МЕБЕЛЬ.", "difficulty": 2 },
        { "id": "lex-hf-11", "word": "комнаты в доме", "hint": "Спальня, гостиная, кухня, ванная, туалет.", "difficulty": 2 },
        { "id": "lex-hf-12", "word": "что на кухне?",  "hint": "Холодильник, плита, посуда, стол, стулья.", "difficulty": 2 },
        { "id": "lex-hf-13", "word": "для чего нужна кровать?", "hint": "Кровать нужна чтобы спать и отдыхать.", "difficulty": 2 },
        { "id": "lex-hf-14", "word": "куда положить одежду?", "hint": "Одежду кладут в шкаф. Книги — на полку. Тарелки — в буфет.", "difficulty": 3 }
      ]
    },
    "professions": {
      "stageId": "professions",
      "note": "Профессии — лексическая тема.",
      "items": [
        { "id": "lex-pr-0",  "word": "врач",          "hint": "Врач лечит людей. Работает в больнице.", "difficulty": 1 },
        { "id": "lex-pr-1",  "word": "учитель",       "hint": "Учитель учит детей. Работает в школе.", "difficulty": 1 },
        { "id": "lex-pr-2",  "word": "повар",         "hint": "Повар готовит еду. Работает на кухне.", "difficulty": 1 },
        { "id": "lex-pr-3",  "word": "водитель",      "hint": "Водитель управляет машиной.", "difficulty": 1 },
        { "id": "lex-pr-4",  "word": "пожарный",      "hint": "Пожарный тушит огонь. Очень смелый!", "difficulty": 2 },
        { "id": "lex-pr-5",  "word": "полицейский",   "hint": "Полицейский охраняет порядок.", "difficulty": 2 },
        { "id": "lex-pr-6",  "word": "продавец",      "hint": "Продавец продаёт товары в магазине.", "difficulty": 2 },
        { "id": "lex-pr-7",  "word": "строитель",     "hint": "Строитель строит дома.", "difficulty": 2 },
        { "id": "lex-pr-8",  "word": "космонавт",     "hint": "Космонавт летит в космос.", "difficulty": 3 },
        { "id": "lex-pr-9",  "word": "художник",      "hint": "Художник рисует картины.", "difficulty": 2 },
        { "id": "lex-pr-10", "word": "кто что делает?", "hint": "Врач лечит. Учитель учит. Повар варит.", "difficulty": 2 },
        { "id": "lex-pr-11", "word": "где работает?",   "hint": "Врач — в больнице. Учитель — в школе. Повар — на кухне.", "difficulty": 2 },
        { "id": "lex-pr-12", "word": "инструменты профессии", "hint": "Врач — стетоскоп. Учитель — мел. Повар — кастрюля.", "difficulty": 3 },
        { "id": "lex-pr-13", "word": "кем ты хочешь стать?", "hint": "Я хочу быть... потому что...", "difficulty": 3 },
        { "id": "lex-pr-14", "word": "профессии мамы и папы", "hint": "Моя мама — ... Мой папа — ... Они работают в...", "difficulty": 3 }
      ]
    }
  },
  "templateCompatibility": {
    "animals_wild":      ["listen-and-choose", "drag-and-match", "memory", "sorting", "puzzle-reveal"],
    "animals_domestic":  ["listen-and-choose", "drag-and-match", "memory", "sorting"],
    "birds":             ["listen-and-choose", "drag-and-match", "sorting", "memory"],
    "vegetables_fruits": ["listen-and-choose", "drag-and-match", "sorting", "memory", "bingo"],
    "clothing":          ["listen-and-choose", "drag-and-match", "sorting", "memory"],
    "transport":         ["listen-and-choose", "drag-and-match", "sorting", "memory", "puzzle-reveal"],
    "body_parts":        ["listen-and-choose", "drag-and-match", "repeat-after-model", "ar-activity"],
    "colors_shapes":     ["listen-and-choose", "drag-and-match", "sorting", "visual-acoustic"],
    "antonyms":          ["listen-and-choose", "minimal-pairs", "drag-and-match", "sorting"],
    "verbs":             ["listen-and-choose", "drag-and-match", "sorting", "story-completion"],
    "grammar_cases":     ["listen-and-choose", "drag-and-match", "repeat-after-model", "story-completion"],
    "seasons_weather":   ["listen-and-choose", "drag-and-match", "sorting", "memory", "story-completion"],
    "house_furniture":   ["listen-and-choose", "drag-and-match", "sorting", "memory"],
    "professions":       ["listen-and-choose", "drag-and-match", "sorting", "story-completion", "narrative-quest"]
  }
}
