{
  "id": "pack_general_phonemic_v1",
  "soundTarget": "phonemic",
  "group": "фонематика",
  "version": 1,
  "description": "Развитие фонематического слуха: различение звуков, позиция в слове, твёрдые/мягкие, звонкие/глухие, количество слогов, анализ слова.",
  "stages": {
    "vowel_consonant": {
      "stageId": "vowel_consonant",
      "note": "Различение гласных и согласных звуков.",
      "items": [
        { "id": "phon-vc-0",  "word": "А — гласный или согласный?",      "hint": "А — гласный. Его можно петь долго: А-А-А!", "difficulty": 1 },
        { "id": "phon-vc-1",  "word": "М — гласный или согласный?",      "hint": "М — согласный. Он не поётся, мычится: ммм.", "difficulty": 1 },
        { "id": "phon-vc-2",  "word": "О — гласный или согласный?",      "hint": "О — гласный. Пой: О-О-О!", "difficulty": 1 },
        { "id": "phon-vc-3",  "word": "С — гласный или согласный?",      "hint": "С — согласный. Сссс — не споёшь!", "difficulty": 1 },
        { "id": "phon-vc-4",  "word": "У — гласный или согласный?",      "hint": "У — гласный. Паровоз гудит: У-У-У!", "difficulty": 1 },
        { "id": "phon-vc-5",  "word": "Р — гласный или согласный?",      "hint": "Р — согласный. Рычит: рррр.", "difficulty": 1 },
        { "id": "phon-vc-6",  "word": "И — гласный или согласный?",      "hint": "И — гласный. Мышка пищит: И-И-И!", "difficulty": 1 },
        { "id": "phon-vc-7",  "word": "Ш — гласный или согласный?",      "hint": "Ш — согласный. Шшш — тихо!", "difficulty": 1 },
        { "id": "phon-vc-8",  "word": "Э — гласный или согласный?",      "hint": "Э — гласный. Можно петь!", "difficulty": 2 },
        { "id": "phon-vc-9",  "word": "Ч — гласный или согласный?",      "hint": "Ч — согласный. Паровоз: ч-ч-ч!", "difficulty": 2 },
        { "id": "phon-vc-10", "word": "Ы — гласный или согласный?",      "hint": "Ы — гласный. Медведь рычит: ы-ы-ы!", "difficulty": 2 },
        { "id": "phon-vc-11", "word": "Л — гласный или согласный?",      "hint": "Л — согласный. Ллл — мягкий звук.", "difficulty": 2 },
        { "id": "phon-vc-12", "word": "Й — гласный или согласный?",      "hint": "Й — согласный (несмотря на краткость).", "difficulty": 3 },
        { "id": "phon-vc-13", "word": "найди гласный: кот",              "hint": "К-О-Т. Гласный: О.", "difficulty": 2 },
        { "id": "phon-vc-14", "word": "найди гласный: рыба",             "hint": "Р-Ы-Б-А. Гласные: Ы и А.", "difficulty": 2 },
        { "id": "phon-vc-15", "word": "найди гласный: слон",             "hint": "С-Л-О-Н. Гласный: О.", "difficulty": 2 },
        { "id": "phon-vc-16", "word": "найди гласные: сова",             "hint": "С-О-В-А. Гласные: О и А.", "difficulty": 2 },
        { "id": "phon-vc-17", "word": "найди гласные: лиса",             "hint": "Л-И-С-А. Гласные: И и А.", "difficulty": 2 },
        { "id": "phon-vc-18", "word": "сколько гласных: мак",            "hint": "М-А-К. Один гласный: А.", "difficulty": 2 },
        { "id": "phon-vc-19", "word": "сколько гласных: кошка",          "hint": "К-О-Ш-К-А. Два гласных: О и А.", "difficulty": 3 }
      ]
    },
    "hard_soft": {
      "stageId": "hard_soft",
      "note": "Различение твёрдых и мягких согласных.",
      "items": [
        { "id": "phon-hs-0",  "word": "С — твёрдый или мягкий в «сом»?",   "hint": "Сом — С твёрдый. Язычок не улыбается.", "difficulty": 2 },
        { "id": "phon-hs-1",  "word": "С — твёрдый или мягкий в «синий»?", "hint": "Синий — С мягкий. Язычок улыбается!", "difficulty": 2 },
        { "id": "phon-hs-2",  "word": "Л — в «лук» твёрдый или мягкий?",   "hint": "Лук — Л твёрдый.", "difficulty": 2 },
        { "id": "phon-hs-3",  "word": "Л — в «лист» твёрдый или мягкий?",  "hint": "Лист — Л мягкий.", "difficulty": 2 },
        { "id": "phon-hs-4",  "word": "Н — в «нос» или «небо»?",           "hint": "Нос — Н твёрдый. Небо — Н мягкий.", "difficulty": 2 },
        { "id": "phon-hs-5",  "word": "Р — в «рак» или «река»?",           "hint": "Рак — Р твёрдый. Река — Р мягкий.", "difficulty": 2 },
        { "id": "phon-hs-6",  "word": "Т — в «тот» или «тень»?",           "hint": "Тот — Т твёрдый. Тень — Т мягкий.", "difficulty": 2 },
        { "id": "phon-hs-7",  "word": "Д — в «дом» или «дерево»?",         "hint": "Дом — Д твёрдый. Дерево — Д мягкий.", "difficulty": 2 },
        { "id": "phon-hs-8",  "word": "пары: мал — мяч",                   "hint": "М в «мал» — твёрдый. М в «мяч» — мягкий.", "difficulty": 3 },
        { "id": "phon-hs-9",  "word": "пары: рад — ряд",                   "hint": "Р в «рад» — твёрдый. Р в «ряд» — мягкий.", "difficulty": 3 },
        { "id": "phon-hs-10", "word": "пары: лук — люк",                   "hint": "Л в «лук» — твёрдый. Л в «люк» — мягкий.", "difficulty": 3 },
        { "id": "phon-hs-11", "word": "пары: нос — нёс",                   "hint": "Н в «нос» — твёрдый. Н в «нёс» — мягкий.", "difficulty": 3 },
        { "id": "phon-hs-12", "word": "всегда мягкий: Й, Ч, Щ",           "hint": "Эти три звука — всегда мягкие, без исключений!", "difficulty": 3 },
        { "id": "phon-hs-13", "word": "всегда твёрдый: Ш, Ж, Ц",          "hint": "Эти три звука — всегда твёрдые, без исключений!", "difficulty": 3 },
        { "id": "phon-hs-14", "word": "твёрдый или мягкий П в «пила»?",   "hint": "Пила — П мягкий (перед И).", "difficulty": 3 },
        { "id": "phon-hs-15", "word": "твёрдый или мягкий В в «вата»?",   "hint": "Вата — В твёрдый.", "difficulty": 3 },
        { "id": "phon-hs-16", "word": "найди мягкий согласный: кит",       "hint": "К-И-Т. К мягкий (перед И).", "difficulty": 3 },
        { "id": "phon-hs-17", "word": "найди мягкий согласный: тигр",      "hint": "Т-И-Г-Р. Т мягкий (перед И).", "difficulty": 3 },
        { "id": "phon-hs-18", "word": "пары: тук — тюк",                   "hint": "Т твёрдый в «тук». Т мягкий в «тюк».", "difficulty": 3 },
        { "id": "phon-hs-19", "word": "пары: сук — сюк (нет слова!)",      "hint": "Сук — настоящее. Сюк — нет. Но С будет мягким.", "difficulty": 4 }
      ]
    },
    "voiced_unvoiced": {
      "stageId": "voiced_unvoiced",
      "note": "Различение звонких и глухих согласных.",
      "items": [
        { "id": "phon-vu-0",  "word": "Б или П: «бочка — почка»",         "hint": "Бочка — Б звонкий. Почка — П глухой.", "difficulty": 2 },
        { "id": "phon-vu-1",  "word": "Д или Т: «дом — том»",             "hint": "Дом — Д звонкий. Том — Т глухой.", "difficulty": 2 },
        { "id": "phon-vu-2",  "word": "Г или К: «год — кот»",             "hint": "Год — Г звонкий. Кот — К глухой.", "difficulty": 2 },
        { "id": "phon-vu-3",  "word": "З или С: «зуб — суп»",             "hint": "Зуб — З звонкий. Суп — С глухой.", "difficulty": 2 },
        { "id": "phon-vu-4",  "word": "Ж или Ш: «жар — шар»",             "hint": "Жар — Ж звонкий. Шар — Ш глухой.", "difficulty": 2 },
        { "id": "phon-vu-5",  "word": "В или Ф: «вата — фата»",           "hint": "Вата — В звонкий. Фата — Ф глухой.", "difficulty": 2 },
        { "id": "phon-vu-6",  "word": "рука к горлу: Б звонкий!",          "hint": "Положи руку на горло: при Б — горло дрожит.", "difficulty": 1 },
        { "id": "phon-vu-7",  "word": "рука к горлу: П глухой!",           "hint": "При П — горло не дрожит. Тихий звук.", "difficulty": 1 },
        { "id": "phon-vu-8",  "word": "найди звонкий: сад или кот?",      "hint": "Сад — С глухой, но Д звонкий. Кот — К глухой, Т глухой.", "difficulty": 3 },
        { "id": "phon-vu-9",  "word": "звонкие в слове «зебра»",          "hint": "З — звонкий, Б — звонкий. Два звонких!", "difficulty": 3 },
        { "id": "phon-vu-10", "word": "пара: коза — коса",                "hint": "Коза — З звонкий. Коса — С глухой.", "difficulty": 3 },
        { "id": "phon-vu-11", "word": "пара: пруд — прут",                "hint": "Пруд — Д звонкий. Прут — Т глухой.", "difficulty": 3 },
        { "id": "phon-vu-12", "word": "пара: гора — кора",                "hint": "Гора — Г звонкий. Кора — К глухой.", "difficulty": 3 },
        { "id": "phon-vu-13", "word": "пара: жить — шить",                "hint": "Жить — Ж звонкий. Шить — Ш глухой.", "difficulty": 3 },
        { "id": "phon-vu-14", "word": "пара: год — кот",                  "hint": "Год — Г звонкий. Кот — К глухой.", "difficulty": 3 },
        { "id": "phon-vu-15", "word": "пара: бок — пок",                  "hint": "Бок — Б звонкий. Пок — нет такого, но П глухой.", "difficulty": 3 },
        { "id": "phon-vu-16", "word": "пара: дар — тар",                  "hint": "Дар — Д звонкий. Тар — нет, но Т глухой.", "difficulty": 3 },
        { "id": "phon-vu-17", "word": "слово с двумя звонкими: зима",     "hint": "З — звонкий, М — звонкий!", "difficulty": 3 },
        { "id": "phon-vu-18", "word": "слово с двумя глухими: кот",       "hint": "К — глухой, Т — глухой!", "difficulty": 3 },
        { "id": "phon-vu-19", "word": "сортировка: звонкие vs глухие согласные", "hint": "Б,В,Г,Д,З,Ж — звонкие. П,Ф,К,Т,С,Ш — глухие.", "difficulty": 4 }
      ]
    },
    "sound_position": {
      "stageId": "sound_position",
      "note": "Позиция звука в слове: начало, середина, конец.",
      "items": [
        { "id": "phon-sp-0",  "word": "где С в «сом»?",                   "hint": "Сом — С в начале слова!", "difficulty": 1 },
        { "id": "phon-sp-1",  "word": "где С в «оса»?",                   "hint": "Оса — С в середине слова!", "difficulty": 2 },
        { "id": "phon-sp-2",  "word": "где С в «нос»?",                   "hint": "Нос — С в конце слова!", "difficulty": 1 },
        { "id": "phon-sp-3",  "word": "где Ш в «шапка»?",                 "hint": "Шапка — Ш в начале!", "difficulty": 1 },
        { "id": "phon-sp-4",  "word": "где Ш в «кошка»?",                 "hint": "Кошка — Ш в середине!", "difficulty": 2 },
        { "id": "phon-sp-5",  "word": "где Ш в «камыш»?",                 "hint": "Камыш — Ш в конце!", "difficulty": 1 },
        { "id": "phon-sp-6",  "word": "где Р в «рак»?",                   "hint": "Рак — Р в начале!", "difficulty": 1 },
        { "id": "phon-sp-7",  "word": "где Р в «гора»?",                  "hint": "Гора — Р в середине!", "difficulty": 2 },
        { "id": "phon-sp-8",  "word": "где Р в «сыр»?",                   "hint": "Сыр — Р в конце!", "difficulty": 1 },
        { "id": "phon-sp-9",  "word": "где Л в «луна»?",                  "hint": "Луна — Л в начале!", "difficulty": 1 },
        { "id": "phon-sp-10", "word": "где Л в «белка»?",                 "hint": "Белка — Л в середине!", "difficulty": 2 },
        { "id": "phon-sp-11", "word": "где Л в «стол»?",                  "hint": "Стол — Л в конце!", "difficulty": 1 },
        { "id": "phon-sp-12", "word": "где К в «кот»?",                   "hint": "Кот — К в начале!", "difficulty": 1 },
        { "id": "phon-sp-13", "word": "где К в «окно»?",                  "hint": "Окно — К в середине!", "difficulty": 2 },
        { "id": "phon-sp-14", "word": "где К в «замок»?",                 "hint": "Замок — К в конце!", "difficulty": 2 },
        { "id": "phon-sp-15", "word": "сортировка С: начало, середина, конец", "hint": "Сом — начало. Оса — середина. Нос — конец.", "difficulty": 3 },
        { "id": "phon-sp-16", "word": "сортировка Р: начало, середина, конец", "hint": "Рак — начало. Гора — середина. Сыр — конец.", "difficulty": 3 },
        { "id": "phon-sp-17", "word": "сортировка Л: начало, середина, конец", "hint": "Луна — начало. Белка — середина. Стол — конец.", "difficulty": 3 },
        { "id": "phon-sp-18", "word": "найди слово где Ж в начале",       "hint": "Жук, жираф, жаба — все начинаются с Ж!", "difficulty": 2 },
        { "id": "phon-sp-19", "word": "найди слово где З в конце",        "hint": "Арбуз, глаз, мороз — З в конце!", "difficulty": 3 },
        { "id": "phon-sp-20", "word": "найди слово где Ч в середине",     "hint": "Бочка, ночник, мячик — Ч в середине!", "difficulty": 3 },
        { "id": "phon-sp-21", "word": "есть ли Ш в слове «машина»?",      "hint": "Ма-ШИ-на — есть Ш! В середине.", "difficulty": 2 },
        { "id": "phon-sp-22", "word": "есть ли Р в слове «лопата»?",      "hint": "Ло-па-та — нет Р в этом слове.", "difficulty": 2 },
        { "id": "phon-sp-23", "word": "есть ли С в слове «кошка»?",       "hint": "Ко-Ш-ка — нет С. Есть Ш.", "difficulty": 3 },
        { "id": "phon-sp-24", "word": "звук-охотник: найди все слова с З", "hint": "Зонт, коза, арбуз, зима — все слова с З!", "difficulty": 3 }
      ]
    },
    "syllable_count": {
      "stageId": "syllable_count",
      "note": "Определение количества слогов в слове.",
      "items": [
        { "id": "phon-sc-0",  "word": "сколько слогов: «дом»?",           "hint": "Дом — 1 слог. Хлопни один раз: ДОМ.", "difficulty": 1 },
        { "id": "phon-sc-1",  "word": "сколько слогов: «мама»?",          "hint": "Ма-ма — 2 слога. Два хлопка!", "difficulty": 1 },
        { "id": "phon-sc-2",  "word": "сколько слогов: «собака»?",        "hint": "Со-ба-ка — 3 слога. Три хлопка!", "difficulty": 2 },
        { "id": "phon-sc-3",  "word": "сколько слогов: «кот»?",           "hint": "Кот — 1 слог. Один хлопок.", "difficulty": 1 },
        { "id": "phon-sc-4",  "word": "сколько слогов: «лиса»?",          "hint": "Ли-са — 2 слога.", "difficulty": 1 },
        { "id": "phon-sc-5",  "word": "сколько слогов: «черепаха»?",      "hint": "Че-ре-па-ха — 4 слога!", "difficulty": 3 },
        { "id": "phon-sc-6",  "word": "сколько слогов: «машина»?",        "hint": "Ма-ши-на — 3 слога.", "difficulty": 2 },
        { "id": "phon-sc-7",  "word": "сколько слогов: «стол»?",          "hint": "Стол — 1 слог.", "difficulty": 1 },
        { "id": "phon-sc-8",  "word": "сколько слогов: «самолёт»?",       "hint": "Са-мо-лёт — 3 слога.", "difficulty": 2 },
        { "id": "phon-sc-9",  "word": "сколько слогов: «ракета»?",        "hint": "Ра-ке-та — 3 слога.", "difficulty": 2 },
        { "id": "phon-sc-10", "word": "сколько слогов: «ёж»?",            "hint": "Ёж — 1 слог.", "difficulty": 1 },
        { "id": "phon-sc-11", "word": "сколько слогов: «радуга»?",        "hint": "Ра-ду-га — 3 слога.", "difficulty": 2 },
        { "id": "phon-sc-12", "word": "сколько слогов: «крокодил»?",      "hint": "Кро-ко-дил — 3 слога.", "difficulty": 3 },
        { "id": "phon-sc-13", "word": "сколько слогов: «пчела»?",         "hint": "Пче-ла — 2 слога.", "difficulty": 2 },
        { "id": "phon-sc-14", "word": "сколько слогов: «осьминог»?",      "hint": "Ось-ми-ног — 3 слога.", "difficulty": 3 },
        { "id": "phon-sc-15", "word": "сортировка по 1, 2, 3 слогам",     "hint": "1 слог: кот, дом, нос. 2 слога: лиса, мама. 3: собака.", "difficulty": 3 },
        { "id": "phon-sc-16", "word": "найди слово с 1 слогом: слон, ваза, рак", "hint": "Слон — 1 слог! Ваза — 2. Рак — 1. Оба по 1!", "difficulty": 2 },
        { "id": "phon-sc-17", "word": "найди слово с 3 слогами: кот, лиса, молоко", "hint": "Молоко — мо-ло-ко — 3 слога!", "difficulty": 2 },
        { "id": "phon-sc-18", "word": "назови 3 слова с 1 слогом",        "hint": "Кот, мяч, нос, лес, дом — все по 1 слогу!", "difficulty": 3 },
        { "id": "phon-sc-19", "word": "назови 3 слова с 2 слогами",       "hint": "Лиса, роза, мама — 2 слога у каждого!", "difficulty": 3 }
      ]
    },
    "first_sound": {
      "stageId": "first_sound",
      "note": "Выделение первого звука в слове.",
      "items": [
        { "id": "phon-fs-0",  "word": "первый звук в «сом»",              "hint": "Со-о-ом... Первый — С!", "difficulty": 1 },
        { "id": "phon-fs-1",  "word": "первый звук в «рак»",              "hint": "Рр-рак... Первый — Р!", "difficulty": 1 },
        { "id": "phon-fs-2",  "word": "первый звук в «лиса»",             "hint": "Лл-лиса... Первый — Л!", "difficulty": 1 },
        { "id": "phon-fs-3",  "word": "первый звук в «шар»",              "hint": "Шш-шар... Первый — Ш!", "difficulty": 1 },
        { "id": "phon-fs-4",  "word": "первый звук в «жук»",              "hint": "Жж-жук... Первый — Ж!", "difficulty": 1 },
        { "id": "phon-fs-5",  "word": "первый звук в «кот»",              "hint": "К-кот... Первый — К!", "difficulty": 1 },
        { "id": "phon-fs-6",  "word": "первый звук в «дом»",              "hint": "Д-дом... Первый — Д!", "difficulty": 1 },
        { "id": "phon-fs-7",  "word": "первый звук в «осень»",            "hint": "О-осень... Первый — О! Гласный.", "difficulty": 2 },
        { "id": "phon-fs-8",  "word": "первый звук в «аист»",             "hint": "А-аист... Первый — А! Гласный.", "difficulty": 1 },
        { "id": "phon-fs-9",  "word": "первый звук в «утка»",             "hint": "У-утка... Первый — У! Гласный.", "difficulty": 1 },
        { "id": "phon-fs-10", "word": "первый звук в «иглы»",             "hint": "И-иглы... Первый — И! Гласный.", "difficulty": 2 },
        { "id": "phon-fs-11", "word": "найди слово с первым звуком С",    "hint": "Сом, собака, сова — все начинаются с С!", "difficulty": 2 },
        { "id": "phon-fs-12", "word": "найди слово с первым звуком Р",    "hint": "Рак, роза, ракета — все начинаются с Р!", "difficulty": 2 },
        { "id": "phon-fs-13", "word": "найди слово с первым звуком Ш",    "hint": "Шар, шапка, шуба — все начинаются с Ш!", "difficulty": 2 },
        { "id": "phon-fs-14", "word": "найди слово с первым звуком К",    "hint": "Кот, кошка, курица — все начинаются с К!", "difficulty": 2 },
        { "id": "phon-fs-15", "word": "сортировка: найди все С-слова",    "hint": "Сом, оса, нос — все содержат С!", "difficulty": 3 },
        { "id": "phon-fs-16", "word": "одинаковый первый звук: сок-сад?", "hint": "Сок — С, сад — С. Одинаковый — С!", "difficulty": 2 },
        { "id": "phon-fs-17", "word": "разный первый звук: рак-лак?",     "hint": "Рак — Р, лак — Л. Разные!", "difficulty": 2 },
        { "id": "phon-fs-18", "word": "придумай слово на звук М",         "hint": "Мама, молоко, мяч — все начинаются с М!", "difficulty": 3 },
        { "id": "phon-fs-19", "word": "придумай слово на звук Б",         "hint": "Бабочка, белка, банан — все с Б!", "difficulty": 3 }
      ]
    },
    "last_sound": {
      "stageId": "last_sound",
      "note": "Выделение последнего звука в слове.",
      "items": [
        { "id": "phon-ls-0",  "word": "последний звук в «кот»",           "hint": "Ко-о-т... Последний — Т!", "difficulty": 1 },
        { "id": "phon-ls-1",  "word": "последний звук в «нос»",           "hint": "Но-о-с... Последний — С!", "difficulty": 1 },
        { "id": "phon-ls-2",  "word": "последний звук в «лук»",           "hint": "Лу-у-к... Последний — К!", "difficulty": 1 },
        { "id": "phon-ls-3",  "word": "последний звук в «сом»",           "hint": "Со-о-м... Последний — М!", "difficulty": 1 },
        { "id": "phon-ls-4",  "word": "последний звук в «рыба»",          "hint": "Рыб-а... Последний — А! Гласный.", "difficulty": 2 },
        { "id": "phon-ls-5",  "word": "последний звук в «луна»",          "hint": "Лун-а... Последний — А! Гласный.", "difficulty": 2 },
        { "id": "phon-ls-6",  "word": "последний звук в «пень»",          "hint": "Пен-ь... Последний — Н мягкий!", "difficulty": 3 },
        { "id": "phon-ls-7",  "word": "последний звук в «мяч»",           "hint": "Мя-ч... Последний — Ч!", "difficulty": 2 },
        { "id": "phon-ls-8",  "word": "последний звук в «ёж»",            "hint": "Ё-ж... Последний — Ж!", "difficulty": 2 },
        { "id": "phon-ls-9",  "word": "последний звук в «малыш»",         "hint": "Малы-ш... Последний — Ш!", "difficulty": 2 },
        { "id": "phon-ls-10", "word": "последний звук в «стол»",          "hint": "Сто-л... Последний — Л!", "difficulty": 2 },
        { "id": "phon-ls-11", "word": "последний звук в «сыр»",           "hint": "Сы-р... Последний — Р!", "difficulty": 2 },
        { "id": "phon-ls-12", "word": "найди слова с последним А",        "hint": "Луна, рыба, рука — все заканчиваются на А!", "difficulty": 3 },
        { "id": "phon-ls-13", "word": "найди слова с последним Т",        "hint": "Кот, бант, мост — заканчиваются на Т!", "difficulty": 3 },
        { "id": "phon-ls-14", "word": "сортировка по последнему звуку",   "hint": "Кот — Т. Нос — С. Мяч — Ч. Стол — Л.", "difficulty": 4 }
      ]
    },
    "minimal_pairs": {
      "stageId": "minimal_pairs",
      "note": "Минимальные пары — различение близких звуков.",
      "items": [
        { "id": "phon-mp-0",  "word": "бочка — почка",  "hint": "Бочка — деревянная. Почка — у дерева или на теле.", "difficulty": 2 },
        { "id": "phon-mp-1",  "word": "дочка — точка",  "hint": "Дочка — девочка. Точка — в конце предложения.", "difficulty": 2 },
        { "id": "phon-mp-2",  "word": "рак — лак",      "hint": "Рак — в реке. Лак — для ногтей.", "difficulty": 3 },
        { "id": "phon-mp-3",  "word": "рот — лот",      "hint": "Рот — на лице. Лот — морской термин.", "difficulty": 3 },
        { "id": "phon-mp-4",  "word": "уши — уси",      "hint": "Уши — слышат. Уси — нет такого.", "difficulty": 2 },
        { "id": "phon-mp-5",  "word": "мак — бак",      "hint": "Мак — цветок. Бак — большой бочонок.", "difficulty": 2 },
        { "id": "phon-mp-6",  "word": "сок — ток",      "hint": "Сок — пить. Ток — электрический.", "difficulty": 2 },
        { "id": "phon-mp-7",  "word": "пол — вол",      "hint": "Пол — под ногами. Вол — большой бык.", "difficulty": 2 },
        { "id": "phon-mp-8",  "word": "лиса — лиза",    "hint": "Лиса — рыжая. Лиза — имя девочки.", "difficulty": 3 },
        { "id": "phon-mp-9",  "word": "игра слов: кот и год", "hint": "Кот — К в начале. Год — Г в начале.", "difficulty": 3 },
        { "id": "phon-mp-10", "word": "банка — панка",  "hint": "Банка — посуда. Панка — нет.", "difficulty": 2 },
        { "id": "phon-mp-11", "word": "дым — тим",      "hint": "Дым — Д звонкий. Тим — Т глухой.", "difficulty": 3 },
        { "id": "phon-mp-12", "word": "жар — шар",      "hint": "Жар — горячо. Шар — круглый.", "difficulty": 2 },
        { "id": "phon-mp-13", "word": "зайка — сайка",  "hint": "Зайка — заяц. Сайка — хлеб.", "difficulty": 3 },
        { "id": "phon-mp-14", "word": "гора — кора",    "hint": "Гора — высокая. Кора — у дерева.", "difficulty": 3 },
        { "id": "phon-mp-15", "word": "лук — люк",      "hint": "Лук — овощ. Люк — отверстие.", "difficulty": 3 },
        { "id": "phon-mp-16", "word": "мал — мял",      "hint": "Мал — маленький. Мял — из «мять».", "difficulty": 4 },
        { "id": "phon-mp-17", "word": "рад — ряд",      "hint": "Рад — доволен. Ряд — строчка.", "difficulty": 4 },
        { "id": "phon-mp-18", "word": "нос — нёс",      "hint": "Нос — на лице. Нёс — из «нести».", "difficulty": 4 },
        { "id": "phon-mp-19", "word": "вол — вёл",      "hint": "Вол — бык. Вёл — из «вести».", "difficulty": 4 }
      ]
    },
    "sound_analysis": {
      "stageId": "sound_analysis",
      "note": "Полный звуковой анализ слова.",
      "items": [
        { "id": "phon-sa-0",  "word": "анализ слова «кот»",               "hint": "К — согласный глухой твёрдый. О — гласный. Т — согласный глухой твёрдый. 3 звука.", "difficulty": 3 },
        { "id": "phon-sa-1",  "word": "анализ слова «сом»",               "hint": "С — согласный глухой твёрдый. О — гласный. М — согласный звонкий твёрдый. 3 звука.", "difficulty": 3 },
        { "id": "phon-sa-2",  "word": "анализ слова «рак»",               "hint": "Р — согласный звонкий твёрдый. А — гласный. К — согласный глухой твёрдый. 3 звука.", "difficulty": 3 },
        { "id": "phon-sa-3",  "word": "анализ слова «лук»",               "hint": "Л — согласный звонкий твёрдый. У — гласный. К — согласный глухой твёрдый.", "difficulty": 3 },
        { "id": "phon-sa-4",  "word": "анализ слова «жук»",               "hint": "Ж — согласный звонкий твёрдый. У — гласный. К — согласный глухой твёрдый.", "difficulty": 3 },
        { "id": "phon-sa-5",  "word": "анализ слова «нос»",               "hint": "Н — согласный звонкий твёрдый. О — гласный. С — согласный глухой твёрдый.", "difficulty": 3 },
        { "id": "phon-sa-6",  "word": "анализ слова «мяч»",               "hint": "М — согласный звонкий мягкий. А — гласный. Ч — согласный глухой мягкий.", "difficulty": 4 },
        { "id": "phon-sa-7",  "word": "анализ слова «лиса»",              "hint": "Л-мягкий, И-гласный, С-твёрдый, А-гласный. 4 звука, 2 слога.", "difficulty": 4 },
        { "id": "phon-sa-8",  "word": "анализ слова «шар»",               "hint": "Ш — согласный глухой твёрдый (всегда!). А — гласный. Р — согласный звонкий твёрдый.", "difficulty": 3 },
        { "id": "phon-sa-9",  "word": "сколько звуков в «мак»?",          "hint": "М-А-К — 3 звука.", "difficulty": 2 },
        { "id": "phon-sa-10", "word": "сколько звуков в «стол»?",         "hint": "С-Т-О-Л — 4 звука.", "difficulty": 3 },
        { "id": "phon-sa-11", "word": "сколько звуков в «кошка»?",        "hint": "К-О-Ш-К-А — 5 звуков.", "difficulty": 3 },
        { "id": "phon-sa-12", "word": "сколько звуков в «ёж»?",           "hint": "Ёж = Й-О-Ж — 3 звука (Ё = ЙО).", "difficulty": 4 },
        { "id": "phon-sa-13", "word": "сравни «кот» и «год»",             "hint": "Кот — К глухой. Год — Г звонкий. Один звук отличается!", "difficulty": 4 },
        { "id": "phon-sa-14", "word": "что изменилось: «сок» → «шок»?",   "hint": "С заменили на Ш. Один звук — другое слово!", "difficulty": 4 }
      ]
    },
    "phonemic_games": {
      "stageId": "phonemic_games",
      "note": "Игровые задания на фонематику: бинго, охотник, сортировка.",
      "items": [
        { "id": "phon-pg-0",  "word": "БИНГО: отмечай слова с С",         "hint": "Слушай слова. Услышал С — отметь на карточке!", "difficulty": 2 },
        { "id": "phon-pg-1",  "word": "БИНГО: отмечай слова с Ш",         "hint": "Слушай слова. Услышал Ш — отметь!", "difficulty": 2 },
        { "id": "phon-pg-2",  "word": "БИНГО: отмечай слова с Р",         "hint": "Услышал Р — отметь на карточке!", "difficulty": 2 },
        { "id": "phon-pg-3",  "word": "ОХОТНИК: поймай все слова с К",    "hint": "Хлопай, когда слышишь К в слове!", "difficulty": 2 },
        { "id": "phon-pg-4",  "word": "ОХОТНИК: поймай все слова с Ч",    "hint": "Хлопай, когда слышишь Ч!", "difficulty": 2 },
        { "id": "phon-pg-5",  "word": "ОХОТНИК: поймай все слова с Л",    "hint": "Хлопай, когда слышишь Л!", "difficulty": 2 },
        { "id": "phon-pg-6",  "word": "ОХОТНИК: поймай все слова с Р и Л","hint": "Хлопай на Р, топай на Л!", "difficulty": 3 },
        { "id": "phon-pg-7",  "word": "СОРТИРОВКА: С или Ш?",             "hint": "Картинки — в нужную корзину: С или Ш.", "difficulty": 3 },
        { "id": "phon-pg-8",  "word": "СОРТИРОВКА: З или Ж?",             "hint": "Картинки — в нужную корзину: З или Ж.", "difficulty": 3 },
        { "id": "phon-pg-9",  "word": "СОРТИРОВКА: Р или Л?",             "hint": "Картинки — в нужную корзину: Р или Л.", "difficulty": 3 },
        { "id": "phon-pg-10", "word": "ПАМЯТЬ: найди пары слово-звук",    "hint": "Переворачивай карточки: найди слово и его первый звук!", "difficulty": 3 },
        { "id": "phon-pg-11", "word": "ЦЕПОЧКА: последний звук = первый следующего слова", "hint": "КОТ → ТИГР → РЫБА → АИСТ... Каждое слово начинается с последнего звука предыдущего!", "difficulty": 4 },
        { "id": "phon-pg-12", "word": "ШИФРОВЩИК: замени первый звук",   "hint": "Кот → Гот → Дот → Сот... Меняем К на другие звуки!", "difficulty": 4 },
        { "id": "phon-pg-13", "word": "РИФМЫ: найди рифму к «кот»",       "hint": "Кот — мот, рот, лот, вот, тот — все рифмуются!", "difficulty": 3 },
        { "id": "phon-pg-14", "word": "РИФМЫ: найди рифму к «мяч»",       "hint": "Мяч — врач, лач, плач — рифмы!", "difficulty": 3 },
        { "id": "phon-pg-15", "word": "РИФМЫ: найди рифму к «сон»",       "hint": "Сон — дон, тон, звон, слон — рифмы!", "difficulty": 3 },
        { "id": "phon-pg-16", "word": "РИФМЫ: найди рифму к «роза»",      "hint": "Роза — коза, поза, угроза — рифмы!", "difficulty": 3 },
        { "id": "phon-pg-17", "word": "ПРИДУМАЙ СЛОВО на звук Д",          "hint": "Дом, дерево, дождь, дыня — твои слова с Д!", "difficulty": 3 },
        { "id": "phon-pg-18", "word": "ПРИДУМАЙ СЛОВО на звук Н",          "hint": "Нос, небо, нитка, нога — слова с Н!", "difficulty": 3 },
        { "id": "phon-pg-19", "word": "ПРИДУМАЙ СЛОВО на звук П",          "hint": "Папа, пчела, пирог, петух — слова с П!", "difficulty": 3 },
        { "id": "phon-pg-20", "word": "БОЛЬШАЯ ОХОТА: слова с тремя согласными подряд", "hint": "Стол, стул, страус — три согласных в начале!", "difficulty": 5 }
      ]
    }
  },
  "templateCompatibility": {
    "vowel_consonant":  ["listen-and-choose", "sorting", "repeat-after-model", "drag-and-match"],
    "hard_soft":        ["listen-and-choose", "sorting", "minimal-pairs", "drag-and-match"],
    "voiced_unvoiced":  ["listen-and-choose", "sorting", "minimal-pairs", "drag-and-match"],
    "sound_position":   ["listen-and-choose", "sorting", "sound-hunter", "drag-and-match"],
    "syllable_count":   ["listen-and-choose", "sorting", "rhythm", "drag-and-match"],
    "first_sound":      ["listen-and-choose", "sound-hunter", "sorting", "bingo"],
    "last_sound":       ["listen-and-choose", "sound-hunter", "sorting"],
    "minimal_pairs":    ["minimal-pairs", "listen-and-choose", "sorting"],
    "sound_analysis":   ["listen-and-choose", "drag-and-match", "sorting", "repeat-after-model"],
    "phonemic_games":   ["bingo", "sound-hunter", "sorting", "memory", "narrative-quest"]
  }
}
