{"layers": [{"ddd": 0, "ty": 4, "ind": 0, "sr": 1, "ip": 0, "op": 90, "st": 0, "ks": {"a": {"k": [0, 0], "a": 0}, "p": {"k": [0, 0], "a": 0}, "s": {"k": [100, 100], "a": 0}, "r": {"k": 0, "a": 0}, "o": {"k": 100, "a": 0}, "sk": {"k": 0, "a": 0}, "sa": {"k": 0, "a": 0}}, "ao": 0, "bm": 0, "shapes": [{"ty": "gr", "it": [{"ty": "el", "d": 1, "p": {"k": [200, 200], "a": 0}, "s": {"k": [380, 380], "a": 0}}, {"ty": "fl", "o": {"k": 100, "a": 0}, "c": {"k": [0.53, 0.81, 0.98, 1], "a": 0}}, {"ty": "tr", "a": {"k": [0, 0], "a": 0}, "p": {"k": [0, 0], "a": 0}, "s": {"a": 1, "k": [{"t": 0, "i": {"x": [1], "y": [1]}, "o": {"x": [0], "y": [0]}, "s": [100, 100]}, {"t": 5, "i": {"x": [1], "y": [1]}, "o": {"x": [0], "y": [0]}, "s": [101.14805029709527, 101.14805029709527]}, {"t": 11, "i": {"x": [1], "y": [1]}, "o": {"x": [0], "y": [0]}, "s": [102.12132034355965, 102.12132034355965]}, {"t": 16, "i": {"x": [1], "y": [1]}, "o": {"x": [0], "y": [0]}, "s": [102.77163859753387, 102.77163859753387]}, {"t": 22, "i": {"x": [1], "y": [1]}, "o": {"x": [0], "y": [0]}, "s": [103, 103]}, {"t": 28, "i": {"x": [1], "y": [1]}, "o": {"x": [0], "y": [0]}, "s": [102.77163859753387, 102.77163859753387]}, {"t": 33, "i": {"x": [1], "y": [1]}, "o": {"x": [0], "y": [0]}, "s": [102.12132034355965, 102.12132034355965]}, {"t": 39, "i": {"x": [1], "y": [1]}, "o": {"x": [0], "y": [0]}, "s": [101.14805029709527, 101.14805029709527]}, {"t": 45, "i": {"x": [1], "y": [1]}, "o": {"x": [0], "y": [0]}, "s": [100, 100]}, {"t": 50, "i": {"x": [1], "y": [1]}, "o": {"x": [0], "y": [0]}, "s": [98.85194970290473, 98.85194970290473]}, {"t": 56, "i": {"x": [1], "y": [1]}, "o": {"x": [0], "y": [0]}, "s": [97.87867965644035, 97.87867965644035]}, {"t": 61, "i": {"x": [1], "y": [1]}, "o": {"x": [0], "y": [0]}, "s": [97.22836140246613, 97.22836140246613]}, {"t": 67, "i": {"x": [1], "y": [1]}, "o": {"x": [0], "y": [0]}, "s": [97, 97]}, {"t": 73, "i": {"x": [1], "y": [1]}, "o": {"x": [0], "y": [0]}, "s": [97.22836140246613, 97.22836140246613]}, {"t": 78, "i": {"x": [1], "y": [1]}, "o": {"x": [0], "y": [0]}, "s": [97.87867965644035, 97.87867965644035]}, {"t": 84, "i": {"x": [1], "y": [1]}, "o": {"x": [0], "y": [0]}, "s": [98.85194970290473, 98.85194970290473]}, {"t": 90, "s": [100, 100]}]}, "r": {"k": 0, "a": 0}, "o": {"k": 100, "a": 0}, "sk": {"k": 0, "a": 0}, "sa": {"k": 0, "a": 0}}]}]}, {"ddd": 0, "ty": 4, "ind": 1, "sr": 1, "ip": 0, "op": 90, "st": 0, "ks": {"a": {"k": [0, 0], "a": 0}, "p": {"k": [0, 0], "a": 0}, "s": {"k": [100, 100], "a": 0}, "r": {"k": 0, "a": 0}, "o": {"k": 100, "a": 0}, "sk": {"k": 0, "a": 0}, "sa": {"k": 0, "a": 0}}, "ao": 0, "bm": 0, "shapes": [{"ty": "gr", "it": [{"ty": "el", "d": 1, "p": {"k": [0, 0], "a": 0}, "s": {"k": [12, 12], "a": 0}}, {"ty": "fl", "o": {"k": 100, "a": 0}, "c": {"k": [1, 0.9, 0.3, 1], "a": 0}}, {"ty": "tr", "a": {"k": [0, 0], "a": 0}, "p": {"a": 1, "k": [{"t": 0, "i": {"x": [1], "y": [1]}, "o": {"x": [0], "y": [0]}, "s": [358, 200]}, {"t": 4, "i": {"x": [1], "y": [1]}, "o": {"x": [0], "y": [0]}, "s": [350.2669295746342, 248.8246851112417]}, {"t": 9, "i": {"x": [1], "y": [1]}, "o": {"x": [0], "y": [0]}, "s": [327.8246851112417, 292.87006986221076]}, {"t": 13, "i": {"x": [1], "y": [1]}, "o": {"x": [0], "y": [0]}, "s": [292.87006986221076, 327.8246851112417]}, {"t": 18, "i": {"x": [1], "y": [1]}, "o": {"x": [0], "y": [0]}, "s": [248.8246851112417, 350.2669295746342]}, {"t": 22, "i": {"x": [1], "y": [1]}, "o": {"x": [0], "y": [0]}, "s": [200, 358]}, {"t": 27, "i": {"x": [1], "y": [1]}, "o": {"x": [0], "y": [0]}, "s": [151.17531488875832, 350.2669295746343]}, {"t": 31, "i": {"x": [1], "y": [1]}, "o": {"x": [0], "y": [0]}, "s": [107.12993013778926, 327.8246851112417]}, {"t": 36, "i": {"x": [1], "y": [1]}, "o": {"x": [0], "y": [0]}, "s": [72.17531488875832, 292.87006986221076]}, {"t": 40, "i": {"x": [1], "y": [1]}, "o": {"x": [0], "y": [0]}, "s": [49.73307042536575, 248.8246851112417]}, {"t": 45, "i": {"x": [1], "y": [1]}, "o": {"x": [0], "y": [0]}, "s": [42, 200.00000000000003]}, {"t": 49, "i": {"x": [1], "y": [1]}, "o": {"x": [0], "y": [0]}, "s": [49.73307042536575, 151.17531488875827]}, {"t": 54, "i": {"x": [1], "y": [1]}, "o": {"x": [0], "y": [0]}, "s": [72.17531488875831, 107.12993013778926]}, {"t": 58, "i": {"x": [1], "y": [1]}, "o": {"x": [0], "y": [0]}, "s": [107.12993013778923, 72.17531488875832]}, {"t": 62, "i": {"x": [1], "y": [1]}, "o": {"x": [0], "y": [0]}, "s": [151.1753148887583, 49.73307042536575]}, {"t": 67, "i": {"x": [1], "y": [1]}, "o": {"x": [0], "y": [0]}, "s": [199.99999999999997, 42]}, {"t": 72, "i": {"x": [1], "y": [1]}, "o": {"x": [0], "y": [0]}, "s": [248.82468511124165, 49.733070425365725]}, {"t": 76, "i": {"x": [1], "y": [1]}, "o": {"x": [0], "y": [0]}, "s": [292.8700698622107, 72.17531488875828]}, {"t": 81, "i": {"x": [1], "y": [1]}, "o": {"x": [0], "y": [0]}, "s": [327.8246851112417, 107.12993013778922]}, {"t": 85, "i": {"x": [1], "y": [1]}, "o": {"x": [0], "y": [0]}, "s": [350.2669295746342, 151.17531488875827]}, {"t": 90, "s": [358, 199.99999999999997]}]}, "s": {"k": [100, 100], "a": 0}, "r": {"k": 0, "a": 0}, "o": {"k": 100, "a": 0}, "sk": {"k": 0, "a": 0}, "sa": {"k": 0, "a": 0}}]}]}, {"ddd": 0, "ty": 4, "ind": 2, "sr": 1, "ip": 0, "op": 90, "st": 0, "ks": {"a": {"k": [0, 0], "a": 0}, "p": {"k": [0, 0], "a": 0}, "s": {"k": [100, 100], "a": 0}, "r": {"k": 0, "a": 0}, "o": {"k": 100, "a": 0}, "sk": {"k": 0, "a": 0}, "sa": {"k": 0, "a": 0}}, "ao": 0, "bm": 0, "shapes": [{"ty": "gr", "it": [{"ty": "el", "d": 1, "p": {"k": [0, 0], "a": 0}, "s": {"k": [12, 12], "a": 0}}, {"ty": "fl", "o": {"k": 100, "a": 0}, "c": {"k": [1, 0.75, 0.59, 1], "a": 0}}, {"ty": "tr", "a": {"k": [0, 0], "a": 0}, "p": {"a": 1, "k": [{"t": 0, "i": {"x": [1], "y": [1]}, "o": {"x": [0], "y": [0]}, "s": [311.7228714274745, 311.7228714274745]}, {"t": 4, "i": {"x": [1], "y": [1]}, "o": {"x": [0], "y": [0]}, "s": [271.7304989588484, 340.77903082176215]}, {"t": 9, "i": {"x": [1], "y": [1]}, "o": {"x": [0], "y": [0]}, "s": [224.7166454763565, 356.05475781403175]}, {"t": 13, "i": {"x": [1], "y": [1]}, "o": {"x": [0], "y": [0]}, "s": [175.28335452364354, 356.05475781403175]}, {"t": 18, "i": {"x": [1], "y": [1]}, "o": {"x": [0], "y": [0]}, "s": [128.2695010411516, 340.77903082176215]}, {"t": 22, "i": {"x": [1], "y": [1]}, "o": {"x": [0], "y": [0]}, "s": [88.2771285725255, 311.7228714274745]}, {"t": 27, "i": {"x": [1], "y": [1]}, "o": {"x": [0], "y": [0]}, "s": [59.22096917823788, 271.7304989588484]}, {"t": 31, "i": {"x": [1], "y": [1]}, "o": {"x": [0], "y": [0]}, "s": [43.945242185968254, 224.7166454763565]}, {"t": 36, "i": {"x": [1], "y": [1]}, "o": {"x": [0], "y": [0]}, "s": [43.945242185968226, 175.28335452364354]}, {"t": 40, "i": {"x": [1], "y": [1]}, "o": {"x": [0], "y": [0]}, "s": [59.22096917823788, 128.2695010411516]}, {"t": 45, "i": {"x": [1], "y": [1]}, "o": {"x": [0], "y": [0]}, "s": [88.27712857252547, 88.2771285725255]}, {"t": 49, "i": {"x": [1], "y": [1]}, "o": {"x": [0], "y": [0]}, "s": [128.26950104115173, 59.22096917823782]}, {"t": 54, "i": {"x": [1], "y": [1]}, "o": {"x": [0], "y": [0]}, "s": [175.28335452364348, 43.945242185968254]}, {"t": 58, "i": {"x": [1], "y": [1]}, "o": {"x": [0], "y": [0]}, "s": [224.71664547635646, 43.945242185968226]}, {"t": 62, "i": {"x": [1], "y": [1]}, "o": {"x": [0], "y": [0]}, "s": [271.7304989588484, 59.22096917823788]}, {"t": 67, "i": {"x": [1], "y": [1]}, "o": {"x": [0], "y": [0]}, "s": [311.7228714274745, 88.27712857252547]}, {"t": 72, "i": {"x": [1], "y": [1]}, "o": {"x": [0], "y": [0]}, "s": [340.77903082176215, 128.26950104115159]}, {"t": 76, "i": {"x": [1], "y": [1]}, "o": {"x": [0], "y": [0]}, "s": [356.05475781403175, 175.28335452364348]}, {"t": 81, "i": {"x": [1], "y": [1]}, "o": {"x": [0], "y": [0]}, "s": [356.05475781403175, 224.71664547635643]}, {"t": 85, "i": {"x": [1], "y": [1]}, "o": {"x": [0], "y": [0]}, "s": [340.77903082176215, 271.73049895884833]}, {"t": 90, "s": [311.7228714274745, 311.7228714274745]}]}, "s": {"k": [100, 100], "a": 0}, "r": {"k": 0, "a": 0}, "o": {"k": 100, "a": 0}, "sk": {"k": 0, "a": 0}, "sa": {"k": 0, "a": 0}}]}]}, {"ddd": 0, "ty": 4, "ind": 3, "sr": 1, "ip": 0, "op": 90, "st": 0, "ks": {"a": {"k": [0, 0], "a": 0}, "p": {"k": [0, 0], "a": 0}, "s": {"k": [100, 100], "a": 0}, "r": {"k": 0, "a": 0}, "o": {"k": 100, "a": 0}, "sk": {"k": 0, "a": 0}, "sa": {"k": 0, "a": 0}}, "ao": 0, "bm": 0, "shapes": [{"ty": "gr", "it": [{"ty": "el", "d": 1, "p": {"k": [0, 0], "a": 0}, "s": {"k": [12, 12], "a": 0}}, {"ty": "fl", "o": {"k": 100, "a": 0}, "c": {"k": [0.76, 0.6, 0.98, 1], "a": 0}}, {"ty": "tr", "a": {"k": [0, 0], "a": 0}, "p": {"a": 1, "k": [{"t": 0, "i": {"x": [1], "y": [1]}, "o": {"x": [0], "y": [0]}, "s": [200, 358]}, {"t": 4, "i": {"x": [1], "y": [1]}, "o": {"x": [0], "y": [0]}, "s": [151.17531488875832, 350.2669295746343]}, {"t": 9, "i": {"x": [1], "y": [1]}, "o": {"x": [0], "y": [0]}, "s": [107.12993013778926, 327.8246851112417]}, {"t": 13, "i": {"x": [1], "y": [1]}, "o": {"x": [0], "y": [0]}, "s": [72.17531488875832, 292.87006986221076]}, {"t": 18, "i": {"x": [1], "y": [1]}, "o": {"x": [0], "y": [0]}, "s": [49.73307042536575, 248.8246851112417]}, {"t": 22, "i": {"x": [1], "y": [1]}, "o": {"x": [0], "y": [0]}, "s": [42, 200.00000000000003]}, {"t": 27, "i": {"x": [1], "y": [1]}, "o": {"x": [0], "y": [0]}, "s": [49.733070425365725, 151.17531488875832]}, {"t": 31, "i": {"x": [1], "y": [1]}, "o": {"x": [0], "y": [0]}, "s": [72.17531488875831, 107.12993013778926]}, {"t": 36, "i": {"x": [1], "y": [1]}, "o": {"x": [0], "y": [0]}, "s": [107.12993013778923, 72.17531488875832]}, {"t": 40, "i": {"x": [1], "y": [1]}, "o": {"x": [0], "y": [0]}, "s": [151.1753148887583, 49.73307042536575]}, {"t": 45, "i": {"x": [1], "y": [1]}, "o": {"x": [0], "y": [0]}, "s": [199.99999999999997, 42]}, {"t": 49, "i": {"x": [1], "y": [1]}, "o": {"x": [0], "y": [0]}, "s": [248.82468511124165, 49.733070425365725]}, {"t": 54, "i": {"x": [1], "y": [1]}, "o": {"x": [0], "y": [0]}, "s": [292.8700698622107, 72.17531488875828]}, {"t": 58, "i": {"x": [1], "y": [1]}, "o": {"x": [0], "y": [0]}, "s": [327.8246851112417, 107.12993013778922]}, {"t": 62, "i": {"x": [1], "y": [1]}, "o": {"x": [0], "y": [0]}, "s": [350.2669295746342, 151.17531488875827]}, {"t": 67, "i": {"x": [1], "y": [1]}, "o": {"x": [0], "y": [0]}, "s": [358, 199.99999999999997]}, {"t": 72, "i": {"x": [1], "y": [1]}, "o": {"x": [0], "y": [0]}, "s": [350.2669295746343, 248.82468511124165]}, {"t": 76, "i": {"x": [1], "y": [1]}, "o": {"x": [0], "y": [0]}, "s": [327.8246851112417, 292.8700698622107]}, {"t": 81, "i": {"x": [1], "y": [1]}, "o": {"x": [0], "y": [0]}, "s": [292.8700698622108, 327.82468511124165]}, {"t": 85, "i": {"x": [1], "y": [1]}, "o": {"x": [0], "y": [0]}, "s": [248.82468511124173, 350.2669295746342]}, {"t": 90, "s": [200.00000000000006, 358]}]}, "s": {"k": [100, 100], "a": 0}, "r": {"k": 0, "a": 0}, "o": {"k": 100, "a": 0}, "sk": {"k": 0, "a": 0}, "sa": {"k": 0, "a": 0}}]}]}, {"ddd": 0, "ty": 4, "ind": 4, "sr": 1, "ip": 0, "op": 90, "st": 0, "ks": {"a": {"k": [0, 0], "a": 0}, "p": {"k": [0, 0], "a": 0}, "s": {"k": [100, 100], "a": 0}, "r": {"k": 0, "a": 0}, "o": {"k": 100, "a": 0}, "sk": {"k": 0, "a": 0}, "sa": {"k": 0, "a": 0}}, "ao": 0, "bm": 0, "shapes": [{"ty": "gr", "it": [{"ty": "el", "d": 1, "p": {"k": [0, 0], "a": 0}, "s": {"k": [12, 12], "a": 0}}, {"ty": "fl", "o": {"k": 100, "a": 0}, "c": {"k": [0.56, 0.93, 0.76, 1], "a": 0}}, {"ty": "tr", "a": {"k": [0, 0], "a": 0}, "p": {"a": 1, "k": [{"t": 0, "i": {"x": [1], "y": [1]}, "o": {"x": [0], "y": [0]}, "s": [88.2771285725255, 311.7228714274745]}, {"t": 4, "i": {"x": [1], "y": [1]}, "o": {"x": [0], "y": [0]}, "s": [59.22096917823788, 271.7304989588484]}, {"t": 9, "i": {"x": [1], "y": [1]}, "o": {"x": [0], "y": [0]}, "s": [43.945242185968254, 224.7166454763565]}, {"t": 13, "i": {"x": [1], "y": [1]}, "o": {"x": [0], "y": [0]}, "s": [43.945242185968226, 175.28335452364354]}, {"t": 18, "i": {"x": [1], "y": [1]}, "o": {"x": [0], "y": [0]}, "s": [59.22096917823788, 128.2695010411516]}, {"t": 22, "i": {"x": [1], "y": [1]}, "o": {"x": [0], "y": [0]}, "s": [88.27712857252547, 88.2771285725255]}, {"t": 27, "i": {"x": [1], "y": [1]}, "o": {"x": [0], "y": [0]}, "s": [128.26950104115159, 59.22096917823788]}, {"t": 31, "i": {"x": [1], "y": [1]}, "o": {"x": [0], "y": [0]}, "s": [175.28335452364348, 43.945242185968254]}, {"t": 36, "i": {"x": [1], "y": [1]}, "o": {"x": [0], "y": [0]}, "s": [224.71664547635646, 43.945242185968226]}, {"t": 40, "i": {"x": [1], "y": [1]}, "o": {"x": [0], "y": [0]}, "s": [271.7304989588484, 59.22096917823788]}, {"t": 45, "i": {"x": [1], "y": [1]}, "o": {"x": [0], "y": [0]}, "s": [311.7228714274745, 88.27712857252547]}, {"t": 49, "i": {"x": [1], "y": [1]}, "o": {"x": [0], "y": [0]}, "s": [340.77903082176215, 128.2695010411517]}, {"t": 54, "i": {"x": [1], "y": [1]}, "o": {"x": [0], "y": [0]}, "s": [356.05475781403175, 175.28335452364348]}, {"t": 58, "i": {"x": [1], "y": [1]}, "o": {"x": [0], "y": [0]}, "s": [356.05475781403175, 224.71664547635643]}, {"t": 62, "i": {"x": [1], "y": [1]}, "o": {"x": [0], "y": [0]}, "s": [340.77903082176215, 271.73049895884833]}, {"t": 67, "i": {"x": [1], "y": [1]}, "o": {"x": [0], "y": [0]}, "s": [311.7228714274745, 311.7228714274745]}, {"t": 72, "i": {"x": [1], "y": [1]}, "o": {"x": [0], "y": [0]}, "s": [271.73049895884844, 340.77903082176215]}, {"t": 76, "i": {"x": [1], "y": [1]}, "o": {"x": [0], "y": [0]}, "s": [224.71664547635652, 356.05475781403175]}, {"t": 81, "i": {"x": [1], "y": [1]}, "o": {"x": [0], "y": [0]}, "s": [175.2833545236437, 356.05475781403175]}, {"t": 85, "i": {"x": [1], "y": [1]}, "o": {"x": [0], "y": [0]}, "s": [128.26950104115153, 340.77903082176203]}, {"t": 90, "s": [88.27712857252563, 311.7228714274747]}]}, "s": {"k": [100, 100], "a": 0}, "r": {"k": 0, "a": 0}, "o": {"k": 100, "a": 0}, "sk": {"k": 0, "a": 0}, "sa": {"k": 0, "a": 0}}]}]}, {"ddd": 0, "ty": 4, "ind": 5, "sr": 1, "ip": 0, "op": 90, "st": 0, "ks": {"a": {"k": [0, 0], "a": 0}, "p": {"k": [0, 0], "a": 0}, "s": {"k": [100, 100], "a": 0}, "r": {"k": 0, "a": 0}, "o": {"k": 100, "a": 0}, "sk": {"k": 0, "a": 0}, "sa": {"k": 0, "a": 0}}, "ao": 0, "bm": 0, "shapes": [{"ty": "gr", "it": [{"ty": "el", "d": 1, "p": {"k": [0, 0], "a": 0}, "s": {"k": [12, 12], "a": 0}}, {"ty": "fl", "o": {"k": 100, "a": 0}, "c": {"k": [1, 0.9, 0.3, 1], "a": 0}}, {"ty": "tr", "a": {"k": [0, 0], "a": 0}, "p": {"a": 1, "k": [{"t": 0, "i": {"x": [1], "y": [1]}, "o": {"x": [0], "y": [0]}, "s": [42, 200.00000000000003]}, {"t": 4, "i": {"x": [1], "y": [1]}, "o": {"x": [0], "y": [0]}, "s": [49.733070425365725, 151.17531488875832]}, {"t": 9, "i": {"x": [1], "y": [1]}, "o": {"x": [0], "y": [0]}, "s": [72.17531488875831, 107.12993013778926]}, {"t": 13, "i": {"x": [1], "y": [1]}, "o": {"x": [0], "y": [0]}, "s": [107.12993013778923, 72.17531488875832]}, {"t": 18, "i": {"x": [1], "y": [1]}, "o": {"x": [0], "y": [0]}, "s": [151.1753148887583, 49.73307042536575]}, {"t": 22, "i": {"x": [1], "y": [1]}, "o": {"x": [0], "y": [0]}, "s": [199.99999999999997, 42]}, {"t": 27, "i": {"x": [1], "y": [1]}, "o": {"x": [0], "y": [0]}, "s": [248.82468511124165, 49.733070425365725]}, {"t": 31, "i": {"x": [1], "y": [1]}, "o": {"x": [0], "y": [0]}, "s": [292.8700698622107, 72.17531488875828]}, {"t": 36, "i": {"x": [1], "y": [1]}, "o": {"x": [0], "y": [0]}, "s": [327.8246851112417, 107.12993013778922]}, {"t": 40, "i": {"x": [1], "y": [1]}, "o": {"x": [0], "y": [0]}, "s": [350.2669295746342, 151.17531488875827]}, {"t": 45, "i": {"x": [1], "y": [1]}, "o": {"x": [0], "y": [0]}, "s": [358, 199.99999999999997]}, {"t": 49, "i": {"x": [1], "y": [1]}, "o": {"x": [0], "y": [0]}, "s": [350.2669295746343, 248.82468511124165]}, {"t": 54, "i": {"x": [1], "y": [1]}, "o": {"x": [0], "y": [0]}, "s": [327.8246851112417, 292.8700698622107]}, {"t": 58, "i": {"x": [1], "y": [1]}, "o": {"x": [0], "y": [0]}, "s": [292.8700698622108, 327.82468511124165]}, {"t": 62, "i": {"x": [1], "y": [1]}, "o": {"x": [0], "y": [0]}, "s": [248.82468511124173, 350.2669295746342]}, {"t": 67, "i": {"x": [1], "y": [1]}, "o": {"x": [0], "y": [0]}, "s": [200.00000000000006, 358]}, {"t": 72, "i": {"x": [1], "y": [1]}, "o": {"x": [0], "y": [0]}, "s": [151.17531488875835, 350.2669295746343]}, {"t": 76, "i": {"x": [1], "y": [1]}, "o": {"x": [0], "y": [0]}, "s": [107.12993013778927, 327.8246851112417]}, {"t": 81, "i": {"x": [1], "y": [1]}, "o": {"x": [0], "y": [0]}, "s": [72.17531488875834, 292.8700698622108]}, {"t": 85, "i": {"x": [1], "y": [1]}, "o": {"x": [0], "y": [0]}, "s": [49.73307042536575, 248.82468511124176]}, {"t": 90, "s": [42, 200.00000000000006]}]}, "s": {"k": [100, 100], "a": 0}, "r": {"k": 0, "a": 0}, "o": {"k": 100, "a": 0}, "sk": {"k": 0, "a": 0}, "sa": {"k": 0, "a": 0}}]}]}, {"ddd": 0, "ty": 4, "ind": 6, "sr": 1, "ip": 0, "op": 90, "st": 0, "ks": {"a": {"k": [0, 0], "a": 0}, "p": {"k": [0, 0], "a": 0}, "s": {"k": [100, 100], "a": 0}, "r": {"k": 0, "a": 0}, "o": {"k": 100, "a": 0}, "sk": {"k": 0, "a": 0}, "sa": {"k": 0, "a": 0}}, "ao": 0, "bm": 0, "shapes": [{"ty": "gr", "it": [{"ty": "el", "d": 1, "p": {"k": [0, 0], "a": 0}, "s": {"k": [12, 12], "a": 0}}, {"ty": "fl", "o": {"k": 100, "a": 0}, "c": {"k": [1, 0.75, 0.59, 1], "a": 0}}, {"ty": "tr", "a": {"k": [0, 0], "a": 0}, "p": {"a": 1, "k": [{"t": 0, "i": {"x": [1], "y": [1]}, "o": {"x": [0], "y": [0]}, "s": [88.27712857252547, 88.2771285725255]}, {"t": 4, "i": {"x": [1], "y": [1]}, "o": {"x": [0], "y": [0]}, "s": [128.26950104115159, 59.22096917823788]}, {"t": 9, "i": {"x": [1], "y": [1]}, "o": {"x": [0], "y": [0]}, "s": [175.28335452364348, 43.945242185968254]}, {"t": 13, "i": {"x": [1], "y": [1]}, "o": {"x": [0], "y": [0]}, "s": [224.71664547635646, 43.945242185968226]}, {"t": 18, "i": {"x": [1], "y": [1]}, "o": {"x": [0], "y": [0]}, "s": [271.7304989588484, 59.22096917823788]}, {"t": 22, "i": {"x": [1], "y": [1]}, "o": {"x": [0], "y": [0]}, "s": [311.7228714274745, 88.27712857252547]}, {"t": 27, "i": {"x": [1], "y": [1]}, "o": {"x": [0], "y": [0]}, "s": [340.77903082176215, 128.26950104115159]}, {"t": 31, "i": {"x": [1], "y": [1]}, "o": {"x": [0], "y": [0]}, "s": [356.05475781403175, 175.28335452364348]}, {"t": 36, "i": {"x": [1], "y": [1]}, "o": {"x": [0], "y": [0]}, "s": [356.05475781403175, 224.71664547635643]}, {"t": 40, "i": {"x": [1], "y": [1]}, "o": {"x": [0], "y": [0]}, "s": [340.77903082176215, 271.73049895884833]}, {"t": 45, "i": {"x": [1], "y": [1]}, "o": {"x": [0], "y": [0]}, "s": [311.7228714274745, 311.7228714274745]}, {"t": 49, "i": {"x": [1], "y": [1]}, "o": {"x": [0], "y": [0]}, "s": [271.73049895884833, 340.77903082176215]}, {"t": 54, "i": {"x": [1], "y": [1]}, "o": {"x": [0], "y": [0]}, "s": [224.71664547635652, 356.05475781403175]}, {"t": 58, "i": {"x": [1], "y": [1]}, "o": {"x": [0], "y": [0]}, "s": [175.2833545236437, 356.05475781403175]}, {"t": 62, "i": {"x": [1], "y": [1]}, "o": {"x": [0], "y": [0]}, "s": [128.26950104115153, 340.77903082176203]}, {"t": 67, "i": {"x": [1], "y": [1]}, "o": {"x": [0], "y": [0]}, "s": [88.27712857252563, 311.7228714274747]}, {"t": 72, "i": {"x": [1], "y": [1]}, "o": {"x": [0], "y": [0]}, "s": [59.22096917823782, 271.73049895884833]}, {"t": 76, "i": {"x": [1], "y": [1]}, "o": {"x": [0], "y": [0]}, "s": [43.945242185968254, 224.71664547635666]}, {"t": 81, "i": {"x": [1], "y": [1]}, "o": {"x": [0], "y": [0]}, "s": [43.945242185968254, 175.28335452364345]}, {"t": 85, "i": {"x": [1], "y": [1]}, "o": {"x": [0], "y": [0]}, "s": [59.220969178237794, 128.26950104115178]}, {"t": 90, "s": [88.27712857252554, 88.27712857252543]}]}, "s": {"k": [100, 100], "a": 0}, "r": {"k": 0, "a": 0}, "o": {"k": 100, "a": 0}, "sk": {"k": 0, "a": 0}, "sa": {"k": 0, "a": 0}}]}]}, {"ddd": 0, "ty": 4, "ind": 7, "sr": 1, "ip": 0, "op": 90, "st": 0, "ks": {"a": {"k": [0, 0], "a": 0}, "p": {"k": [0, 0], "a": 0}, "s": {"k": [100, 100], "a": 0}, "r": {"k": 0, "a": 0}, "o": {"k": 100, "a": 0}, "sk": {"k": 0, "a": 0}, "sa": {"k": 0, "a": 0}}, "ao": 0, "bm": 0, "shapes": [{"ty": "gr", "it": [{"ty": "el", "d": 1, "p": {"k": [0, 0], "a": 0}, "s": {"k": [12, 12], "a": 0}}, {"ty": "fl", "o": {"k": 100, "a": 0}, "c": {"k": [0.76, 0.6, 0.98, 1], "a": 0}}, {"ty": "tr", "a": {"k": [0, 0], "a": 0}, "p": {"a": 1, "k": [{"t": 0, "i": {"x": [1], "y": [1]}, "o": {"x": [0], "y": [0]}, "s": [199.99999999999997, 42]}, {"t": 4, "i": {"x": [1], "y": [1]}, "o": {"x": [0], "y": [0]}, "s": [248.82468511124165, 49.733070425365725]}, {"t": 9, "i": {"x": [1], "y": [1]}, "o": {"x": [0], "y": [0]}, "s": [292.8700698622107, 72.17531488875828]}, {"t": 13, "i": {"x": [1], "y": [1]}, "o": {"x": [0], "y": [0]}, "s": [327.8246851112417, 107.12993013778922]}, {"t": 18, "i": {"x": [1], "y": [1]}, "o": {"x": [0], "y": [0]}, "s": [350.2669295746342, 151.17531488875827]}, {"t": 22, "i": {"x": [1], "y": [1]}, "o": {"x": [0], "y": [0]}, "s": [358, 199.99999999999997]}, {"t": 27, "i": {"x": [1], "y": [1]}, "o": {"x": [0], "y": [0]}, "s": [350.2669295746343, 248.82468511124165]}, {"t": 31, "i": {"x": [1], "y": [1]}, "o": {"x": [0], "y": [0]}, "s": [327.8246851112417, 292.8700698622107]}, {"t": 36, "i": {"x": [1], "y": [1]}, "o": {"x": [0], "y": [0]}, "s": [292.8700698622108, 327.82468511124165]}, {"t": 40, "i": {"x": [1], "y": [1]}, "o": {"x": [0], "y": [0]}, "s": [248.82468511124173, 350.2669295746342]}, {"t": 45, "i": {"x": [1], "y": [1]}, "o": {"x": [0], "y": [0]}, "s": [200.00000000000006, 358]}, {"t": 49, "i": {"x": [1], "y": [1]}, "o": {"x": [0], "y": [0]}, "s": [151.17531488875835, 350.2669295746343]}, {"t": 54, "i": {"x": [1], "y": [1]}, "o": {"x": [0], "y": [0]}, "s": [107.12993013778927, 327.8246851112417]}, {"t": 58, "i": {"x": [1], "y": [1]}, "o": {"x": [0], "y": [0]}, "s": [72.17531488875834, 292.8700698622108]}, {"t": 62, "i": {"x": [1], "y": [1]}, "o": {"x": [0], "y": [0]}, "s": [49.73307042536575, 248.82468511124176]}, {"t": 67, "i": {"x": [1], "y": [1]}, "o": {"x": [0], "y": [0]}, "s": [42, 200.00000000000006]}, {"t": 72, "i": {"x": [1], "y": [1]}, "o": {"x": [0], "y": [0]}, "s": [49.733070425365725, 151.17531488875835]}, {"t": 76, "i": {"x": [1], "y": [1]}, "o": {"x": [0], "y": [0]}, "s": [72.17531488875827, 107.1299301377893]}, {"t": 81, "i": {"x": [1], "y": [1]}, "o": {"x": [0], "y": [0]}, "s": [107.12993013778919, 72.17531488875834]}, {"t": 85, "i": {"x": [1], "y": [1]}, "o": {"x": [0], "y": [0]}, "s": [151.17531488875824, 49.73307042536575]}, {"t": 90, "s": [199.99999999999994, 42]}]}, "s": {"k": [100, 100], "a": 0}, "r": {"k": 0, "a": 0}, "o": {"k": 100, "a": 0}, "sk": {"k": 0, "a": 0}, "sa": {"k": 0, "a": 0}}]}]}, {"ddd": 0, "ty": 4, "ind": 8, "sr": 1, "ip": 0, "op": 90, "st": 0, "ks": {"a": {"k": [0, 0], "a": 0}, "p": {"k": [0, 0], "a": 0}, "s": {"k": [100, 100], "a": 0}, "r": {"k": 0, "a": 0}, "o": {"k": 100, "a": 0}, "sk": {"k": 0, "a": 0}, "sa": {"k": 0, "a": 0}}, "ao": 0, "bm": 0, "shapes": [{"ty": "gr", "it": [{"ty": "el", "d": 1, "p": {"k": [0, 0], "a": 0}, "s": {"k": [12, 12], "a": 0}}, {"ty": "fl", "o": {"k": 100, "a": 0}, "c": {"k": [0.56, 0.93, 0.76, 1], "a": 0}}, {"ty": "tr", "a": {"k": [0, 0], "a": 0}, "p": {"a": 1, "k": [{"t": 0, "i": {"x": [1], "y": [1]}, "o": {"x": [0], "y": [0]}, "s": [311.7228714274745, 88.27712857252547]}, {"t": 4, "i": {"x": [1], "y": [1]}, "o": {"x": [0], "y": [0]}, "s": [340.77903082176215, 128.26950104115159]}, {"t": 9, "i": {"x": [1], "y": [1]}, "o": {"x": [0], "y": [0]}, "s": [356.05475781403175, 175.28335452364348]}, {"t": 13, "i": {"x": [1], "y": [1]}, "o": {"x": [0], "y": [0]}, "s": [356.05475781403175, 224.71664547635643]}, {"t": 18, "i": {"x": [1], "y": [1]}, "o": {"x": [0], "y": [0]}, "s": [340.77903082176215, 271.73049895884833]}, {"t": 22, "i": {"x": [1], "y": [1]}, "o": {"x": [0], "y": [0]}, "s": [311.7228714274745, 311.7228714274745]}, {"t": 27, "i": {"x": [1], "y": [1]}, "o": {"x": [0], "y": [0]}, "s": [271.73049895884844, 340.77903082176215]}, {"t": 31, "i": {"x": [1], "y": [1]}, "o": {"x": [0], "y": [0]}, "s": [224.71664547635652, 356.05475781403175]}, {"t": 36, "i": {"x": [1], "y": [1]}, "o": {"x": [0], "y": [0]}, "s": [175.2833545236437, 356.05475781403175]}, {"t": 40, "i": {"x": [1], "y": [1]}, "o": {"x": [0], "y": [0]}, "s": [128.26950104115153, 340.77903082176203]}, {"t": 45, "i": {"x": [1], "y": [1]}, "o": {"x": [0], "y": [0]}, "s": [88.27712857252563, 311.7228714274747]}, {"t": 49, "i": {"x": [1], "y": [1]}, "o": {"x": [0], "y": [0]}, "s": [59.22096917823782, 271.73049895884833]}, {"t": 54, "i": {"x": [1], "y": [1]}, "o": {"x": [0], "y": [0]}, "s": [43.945242185968254, 224.71664547635666]}, {"t": 58, "i": {"x": [1], "y": [1]}, "o": {"x": [0], "y": [0]}, "s": [43.945242185968254, 175.28335452364345]}, {"t": 62, "i": {"x": [1], "y": [1]}, "o": {"x": [0], "y": [0]}, "s": [59.220969178237794, 128.26950104115178]}, {"t": 67, "i": {"x": [1], "y": [1]}, "o": {"x": [0], "y": [0]}, "s": [88.27712857252554, 88.27712857252543]}, {"t": 72, "i": {"x": [1], "y": [1]}, "o": {"x": [0], "y": [0]}, "s": [128.26950104115141, 59.220969178237965]}, {"t": 76, "i": {"x": [1], "y": [1]}, "o": {"x": [0], "y": [0]}, "s": [175.2833545236436, 43.945242185968226]}, {"t": 81, "i": {"x": [1], "y": [1]}, "o": {"x": [0], "y": [0]}, "s": [224.71664547635626, 43.945242185968226]}, {"t": 85, "i": {"x": [1], "y": [1]}, "o": {"x": [0], "y": [0]}, "s": [271.73049895884844, 59.22096917823791]}, {"t": 90, "s": [311.7228714274744, 88.27712857252534]}]}, "s": {"k": [100, 100], "a": 0}, "r": {"k": 0, "a": 0}, "o": {"k": 100, "a": 0}, "sk": {"k": 0, "a": 0}, "sa": {"k": 0, "a": 0}}]}]}, {"ddd": 0, "ty": 4, "ind": 9, "sr": 1, "ip": 0, "op": 90, "st": 0, "ks": {"a": {"k": [0, 0], "a": 0}, "p": {"k": [0, 0], "a": 0}, "s": {"k": [100, 100], "a": 0}, "r": {"k": 0, "a": 0}, "o": {"k": 100, "a": 0}, "sk": {"k": 0, "a": 0}, "sa": {"k": 0, "a": 0}}, "ao": 0, "bm": 0, "shapes": [{"ty": "gr", "it": [{"ty": "rc", "d": 1, "p": {"k": [155, 212], "a": 0}, "s": {"k": [88, 118], "a": 0}, "r": {"k": 10, "a": 0}}, {"ty": "fl", "o": {"k": 100, "a": 0}, "c": {"k": [0.76, 0.6, 0.98, 1], "a": 0}}, {"ty": "tr", "a": {"k": [0, 0], "a": 0}, "p": {"k": [0, 0], "a": 0}, "s": {"a": 1, "k": [{"t": 0, "i": {"x": [1], "y": [1]}, "o": {"x": [0], "y": [0]}, "s": [0, 100]}, {"t": 18, "i": {"x": [1], "y": [1]}, "o": {"x": [0], "y": [0]}, "s": [100, 100]}, {"t": 90, "s": [100, 100]}]}, "r": {"k": 0, "a": 0}, "o": {"k": 100, "a": 0}, "sk": {"k": 0, "a": 0}, "sa": {"k": 0, "a": 0}}]}]}, {"ddd": 0, "ty": 4, "ind": 10, "sr": 1, "ip": 0, "op": 90, "st": 0, "ks": {"a": {"k": [0, 0], "a": 0}, "p": {"k": [0, 0], "a": 0}, "s": {"k": [100, 100], "a": 0}, "r": {"k": 0, "a": 0}, "o": {"k": 100, "a": 0}, "sk": {"k": 0, "a": 0}, "sa": {"k": 0, "a": 0}}, "ao": 0, "bm": 0, "shapes": [{"ty": "gr", "it": [{"ty": "rc", "d": 1, "p": {"k": [155, 182], "a": 0}, "s": {"k": [55, 5], "a": 0}, "r": {"k": 3, "a": 0}}, {"ty": "fl", "o": {"k": 50, "a": 0}, "c": {"k": [1, 1, 1, 1], "a": 0}}, {"ty": "tr", "a": {"k": [0, 0], "a": 0}, "p": {"k": [0, 0], "a": 0}, "s": {"k": [100, 100], "a": 0}, "r": {"k": 0, "a": 0}, "o": {"a": 1, "k": [{"t": 0, "i": {"x": [1], "y": [1]}, "o": {"x": [0], "y": [0]}, "s": [0]}, {"t": 22, "i": {"x": [1], "y": [1]}, "o": {"x": [0], "y": [0]}, "s": [50]}, {"t": 90, "s": [50]}]}, "sk": {"k": 0, "a": 0}, "sa": {"k": 0, "a": 0}}]}]}, {"ddd": 0, "ty": 4, "ind": 11, "sr": 1, "ip": 0, "op": 90, "st": 0, "ks": {"a": {"k": [0, 0], "a": 0}, "p": {"k": [0, 0], "a": 0}, "s": {"k": [100, 100], "a": 0}, "r": {"k": 0, "a": 0}, "o": {"k": 100, "a": 0}, "sk": {"k": 0, "a": 0}, "sa": {"k": 0, "a": 0}}, "ao": 0, "bm": 0, "shapes": [{"ty": "gr", "it": [{"ty": "rc", "d": 1, "p": {"k": [155, 202], "a": 0}, "s": {"k": [55, 5], "a": 0}, "r": {"k": 3, "a": 0}}, {"ty": "fl", "o": {"k": 50, "a": 0}, "c": {"k": [1, 1, 1, 1], "a": 0}}, {"ty": "tr", "a": {"k": [0, 0], "a": 0}, "p": {"k": [0, 0], "a": 0}, "s": {"k": [100, 100], "a": 0}, "r": {"k": 0, "a": 0}, "o": {"a": 1, "k": [{"t": 0, "i": {"x": [1], "y": [1]}, "o": {"x": [0], "y": [0]}, "s": [0]}, {"t": 22, "i": {"x": [1], "y": [1]}, "o": {"x": [0], "y": [0]}, "s": [50]}, {"t": 90, "s": [50]}]}, "sk": {"k": 0, "a": 0}, "sa": {"k": 0, "a": 0}}]}]}, {"ddd": 0, "ty": 4, "ind": 12, "sr": 1, "ip": 0, "op": 90, "st": 0, "ks": {"a": {"k": [0, 0], "a": 0}, "p": {"k": [0, 0], "a": 0}, "s": {"k": [100, 100], "a": 0}, "r": {"k": 0, "a": 0}, "o": {"k": 100, "a": 0}, "sk": {"k": 0, "a": 0}, "sa": {"k": 0, "a": 0}}, "ao": 0, "bm": 0, "shapes": [{"ty": "gr", "it": [{"ty": "rc", "d": 1, "p": {"k": [155, 222], "a": 0}, "s": {"k": [55, 5], "a": 0}, "r": {"k": 3, "a": 0}}, {"ty": "fl", "o": {"k": 50, "a": 0}, "c": {"k": [1, 1, 1, 1], "a": 0}}, {"ty": "tr", "a": {"k": [0, 0], "a": 0}, "p": {"k": [0, 0], "a": 0}, "s": {"k": [100, 100], "a": 0}, "r": {"k": 0, "a": 0}, "o": {"a": 1, "k": [{"t": 0, "i": {"x": [1], "y": [1]}, "o": {"x": [0], "y": [0]}, "s": [0]}, {"t": 22, "i": {"x": [1], "y": [1]}, "o": {"x": [0], "y": [0]}, "s": [50]}, {"t": 90, "s": [50]}]}, "sk": {"k": 0, "a": 0}, "sa": {"k": 0, "a": 0}}]}]}, {"ddd": 0, "ty": 4, "ind": 13, "sr": 1, "ip": 0, "op": 90, "st": 0, "ks": {"a": {"k": [0, 0], "a": 0}, "p": {"k": [0, 0], "a": 0}, "s": {"k": [100, 100], "a": 0}, "r": {"k": 0, "a": 0}, "o": {"k": 100, "a": 0}, "sk": {"k": 0, "a": 0}, "sa": {"k": 0, "a": 0}}, "ao": 0, "bm": 0, "shapes": [{"ty": "gr", "it": [{"ty": "rc", "d": 1, "p": {"k": [155, 242], "a": 0}, "s": {"k": [55, 5], "a": 0}, "r": {"k": 3, "a": 0}}, {"ty": "fl", "o": {"k": 50, "a": 0}, "c": {"k": [1, 1, 1, 1], "a": 0}}, {"ty": "tr", "a": {"k": [0, 0], "a": 0}, "p": {"k": [0, 0], "a": 0}, "s": {"k": [100, 100], "a": 0}, "r": {"k": 0, "a": 0}, "o": {"a": 1, "k": [{"t": 0, "i": {"x": [1], "y": [1]}, "o": {"x": [0], "y": [0]}, "s": [0]}, {"t": 22, "i": {"x": [1], "y": [1]}, "o": {"x": [0], "y": [0]}, "s": [50]}, {"t": 90, "s": [50]}]}, "sk": {"k": 0, "a": 0}, "sa": {"k": 0, "a": 0}}]}]}, {"ddd": 0, "ty": 4, "ind": 14, "sr": 1, "ip": 0, "op": 90, "st": 0, "ks": {"a": {"k": [0, 0], "a": 0}, "p": {"k": [0, 0], "a": 0}, "s": {"k": [100, 100], "a": 0}, "r": {"k": 0, "a": 0}, "o": {"k": 100, "a": 0}, "sk": {"k": 0, "a": 0}, "sa": {"k": 0, "a": 0}}, "ao": 0, "bm": 0, "shapes": [{"ty": "gr", "it": [{"ty": "rc", "d": 1, "p": {"k": [245, 212], "a": 0}, "s": {"k": [88, 118], "a": 0}, "r": {"k": 10, "a": 0}}, {"ty": "fl", "o": {"k": 100, "a": 0}, "c": {"k": [1, 0.75, 0.59, 1], "a": 0}}, {"ty": "tr", "a": {"k": [0, 0], "a": 0}, "p": {"k": [0, 0], "a": 0}, "s": {"a": 1, "k": [{"t": 5, "i": {"x": [1], "y": [1]}, "o": {"x": [0], "y": [0]}, "s": [0, 100]}, {"t": 23, "i": {"x": [1], "y": [1]}, "o": {"x": [0], "y": [0]}, "s": [100, 100]}, {"t": 90, "s": [100, 100]}]}, "r": {"k": 0, "a": 0}, "o": {"k": 100, "a": 0}, "sk": {"k": 0, "a": 0}, "sa": {"k": 0, "a": 0}}]}]}, {"ddd": 0, "ty": 4, "ind": 15, "sr": 1, "ip": 0, "op": 90, "st": 0, "ks": {"a": {"k": [0, 0], "a": 0}, "p": {"k": [0, 0], "a": 0}, "s": {"k": [100, 100], "a": 0}, "r": {"k": 0, "a": 0}, "o": {"k": 100, "a": 0}, "sk": {"k": 0, "a": 0}, "sa": {"k": 0, "a": 0}}, "ao": 0, "bm": 0, "shapes": [{"ty": "gr", "it": [{"ty": "el", "d": 1, "p": {"k": [245, 200], "a": 0}, "s": {"k": [45, 45], "a": 0}}, {"ty": "fl", "o": {"k": 100, "a": 0}, "c": {"k": [1, 0.9, 0.3, 1], "a": 0}}, {"ty": "tr", "a": {"k": [0, 0], "a": 0}, "p": {"k": [0, 0], "a": 0}, "s": {"k": [100, 100], "a": 0}, "r": {"k": 0, "a": 0}, "o": {"a": 1, "k": [{"t": 10, "i": {"x": [1], "y": [1]}, "o": {"x": [0], "y": [0]}, "s": [0]}, {"t": 28, "i": {"x": [1], "y": [1]}, "o": {"x": [0], "y": [0]}, "s": [100]}, {"t": 90, "s": [100]}]}, "sk": {"k": 0, "a": 0}, "sa": {"k": 0, "a": 0}}]}]}, {"ddd": 0, "ty": 4, "ind": 16, "sr": 1, "ip": 0, "op": 90, "st": 0, "ks": {"a": {"k": [0, 0], "a": 0}, "p": {"k": [0, 0], "a": 0}, "s": {"k": [100, 100], "a": 0}, "r": {"k": 0, "a": 0}, "o": {"k": 100, "a": 0}, "sk": {"k": 0, "a": 0}, "sa": {"k": 0, "a": 0}}, "ao": 0, "bm": 0, "shapes": [{"ty": "gr", "it": [{"ty": "rc", "d": 1, "p": {"k": [200, 212], "a": 0}, "s": {"k": [10, 118], "a": 0}, "r": {"k": 4, "a": 0}}, {"ty": "fl", "o": {"k": 100, "a": 0}, "c": {"k": [0.15, 0.12, 0.25, 1], "a": 0}}, {"ty": "tr", "a": {"k": [0, 0], "a": 0}, "p": {"k": [0, 0], "a": 0}, "s": {"k": [100, 100], "a": 0}, "r": {"k": 0, "a": 0}, "o": {"k": 100, "a": 0}, "sk": {"k": 0, "a": 0}, "sa": {"k": 0, "a": 0}}]}]}, {"ddd": 0, "ty": 4, "ind": 17, "sr": 1, "ip": 0, "op": 90, "st": 0, "ks": {"a": {"k": [0, 0], "a": 0}, "p": {"k": [0, 0], "a": 0}, "s": {"k": [100, 100], "a": 0}, "r": {"k": 0, "a": 0}, "o": {"k": 100, "a": 0}, "sk": {"k": 0, "a": 0}, "sa": {"k": 0, "a": 0}}, "ao": 0, "bm": 0, "shapes": [{"ty": "gr", "it": [{"ty": "el", "d": 1, "p": {"k": [155, 128], "a": 0}, "s": {"k": [16, 16], "a": 0}}, {"ty": "fl", "o": {"k": 100, "a": 0}, "c": {"k": [1, 0.9, 0.3, 1], "a": 0}}, {"ty": "tr", "a": {"k": [0, 0], "a": 0}, "p": {"k": [0, 0], "a": 0}, "s": {"a": 1, "k": [{"t": 25, "i": {"x": [1], "y": [1]}, "o": {"x": [0], "y": [0]}, "s": [0, 0]}, {"t": 37, "i": {"x": [1], "y": [1]}, "o": {"x": [0], "y": [0]}, "s": [120, 120]}, {"t": 42, "i": {"x": [1], "y": [1]}, "o": {"x": [0], "y": [0]}, "s": [100, 100]}, {"t": 90, "s": [100, 100]}]}, "r": {"k": 0, "a": 0}, "o": {"a": 1, "k": [{"t": 25, "i": {"x": [1], "y": [1]}, "o": {"x": [0], "y": [0]}, "s": [0]}, {"t": 35, "i": {"x": [1], "y": [1]}, "o": {"x": [0], "y": [0]}, "s": [100]}, {"t": 90, "s": [100]}]}, "sk": {"k": 0, "a": 0}, "sa": {"k": 0, "a": 0}}]}]}, {"ddd": 0, "ty": 4, "ind": 18, "sr": 1, "ip": 0, "op": 90, "st": 0, "ks": {"a": {"k": [0, 0], "a": 0}, "p": {"k": [0, 0], "a": 0}, "s": {"k": [100, 100], "a": 0}, "r": {"k": 0, "a": 0}, "o": {"k": 100, "a": 0}, "sk": {"k": 0, "a": 0}, "sa": {"k": 0, "a": 0}}, "ao": 0, "bm": 0, "shapes": [{"ty": "gr", "it": [{"ty": "el", "d": 1, "p": {"k": [188, 108], "a": 0}, "s": {"k": [16, 16], "a": 0}}, {"ty": "fl", "o": {"k": 100, "a": 0}, "c": {"k": [1, 0.9, 0.3, 1], "a": 0}}, {"ty": "tr", "a": {"k": [0, 0], "a": 0}, "p": {"k": [0, 0], "a": 0}, "s": {"a": 1, "k": [{"t": 33, "i": {"x": [1], "y": [1]}, "o": {"x": [0], "y": [0]}, "s": [0, 0]}, {"t": 45, "i": {"x": [1], "y": [1]}, "o": {"x": [0], "y": [0]}, "s": [120, 120]}, {"t": 50, "i": {"x": [1], "y": [1]}, "o": {"x": [0], "y": [0]}, "s": [100, 100]}, {"t": 90, "s": [100, 100]}]}, "r": {"k": 0, "a": 0}, "o": {"a": 1, "k": [{"t": 33, "i": {"x": [1], "y": [1]}, "o": {"x": [0], "y": [0]}, "s": [0]}, {"t": 43, "i": {"x": [1], "y": [1]}, "o": {"x": [0], "y": [0]}, "s": [100]}, {"t": 90, "s": [100]}]}, "sk": {"k": 0, "a": 0}, "sa": {"k": 0, "a": 0}}]}]}, {"ddd": 0, "ty": 4, "ind": 19, "sr": 1, "ip": 0, "op": 90, "st": 0, "ks": {"a": {"k": [0, 0], "a": 0}, "p": {"k": [0, 0], "a": 0}, "s": {"k": [100, 100], "a": 0}, "r": {"k": 0, "a": 0}, "o": {"k": 100, "a": 0}, "sk": {"k": 0, "a": 0}, "sa": {"k": 0, "a": 0}}, "ao": 0, "bm": 0, "shapes": [{"ty": "gr", "it": [{"ty": "el", "d": 1, "p": {"k": [212, 104], "a": 0}, "s": {"k": [16, 16], "a": 0}}, {"ty": "fl", "o": {"k": 100, "a": 0}, "c": {"k": [1, 0.9, 0.3, 1], "a": 0}}, {"ty": "tr", "a": {"k": [0, 0], "a": 0}, "p": {"k": [0, 0], "a": 0}, "s": {"a": 1, "k": [{"t": 41, "i": {"x": [1], "y": [1]}, "o": {"x": [0], "y": [0]}, "s": [0, 0]}, {"t": 53, "i": {"x": [1], "y": [1]}, "o": {"x": [0], "y": [0]}, "s": [120, 120]}, {"t": 58, "i": {"x": [1], "y": [1]}, "o": {"x": [0], "y": [0]}, "s": [100, 100]}, {"t": 90, "s": [100, 100]}]}, "r": {"k": 0, "a": 0}, "o": {"a": 1, "k": [{"t": 41, "i": {"x": [1], "y": [1]}, "o": {"x": [0], "y": [0]}, "s": [0]}, {"t": 51, "i": {"x": [1], "y": [1]}, "o": {"x": [0], "y": [0]}, "s": [100]}, {"t": 90, "s": [100]}]}, "sk": {"k": 0, "a": 0}, "sa": {"k": 0, "a": 0}}]}]}, {"ddd": 0, "ty": 4, "ind": 20, "sr": 1, "ip": 0, "op": 90, "st": 0, "ks": {"a": {"k": [0, 0], "a": 0}, "p": {"k": [0, 0], "a": 0}, "s": {"k": [100, 100], "a": 0}, "r": {"k": 0, "a": 0}, "o": {"k": 100, "a": 0}, "sk": {"k": 0, "a": 0}, "sa": {"k": 0, "a": 0}}, "ao": 0, "bm": 0, "shapes": [{"ty": "gr", "it": [{"ty": "el", "d": 1, "p": {"k": [240, 118], "a": 0}, "s": {"k": [16, 16], "a": 0}}, {"ty": "fl", "o": {"k": 100, "a": 0}, "c": {"k": [1, 0.9, 0.3, 1], "a": 0}}, {"ty": "tr", "a": {"k": [0, 0], "a": 0}, "p": {"k": [0, 0], "a": 0}, "s": {"a": 1, "k": [{"t": 49, "i": {"x": [1], "y": [1]}, "o": {"x": [0], "y": [0]}, "s": [0, 0]}, {"t": 61, "i": {"x": [1], "y": [1]}, "o": {"x": [0], "y": [0]}, "s": [120, 120]}, {"t": 66, "i": {"x": [1], "y": [1]}, "o": {"x": [0], "y": [0]}, "s": [100, 100]}, {"t": 90, "s": [100, 100]}]}, "r": {"k": 0, "a": 0}, "o": {"a": 1, "k": [{"t": 49, "i": {"x": [1], "y": [1]}, "o": {"x": [0], "y": [0]}, "s": [0]}, {"t": 59, "i": {"x": [1], "y": [1]}, "o": {"x": [0], "y": [0]}, "s": [100]}, {"t": 90, "s": [100]}]}, "sk": {"k": 0, "a": 0}, "sa": {"k": 0, "a": 0}}]}]}, {"ddd": 0, "ty": 4, "ind": 21, "sr": 1, "ip": 0, "op": 90, "st": 0, "ks": {"a": {"k": [0, 0], "a": 0}, "p": {"k": [0, 0], "a": 0}, "s": {"k": [100, 100], "a": 0}, "r": {"k": 0, "a": 0}, "o": {"k": 100, "a": 0}, "sk": {"k": 0, "a": 0}, "sa": {"k": 0, "a": 0}}, "ao": 0, "bm": 0, "shapes": [{"ty": "gr", "it": [{"ty": "el", "d": 1, "p": {"k": [170, 88], "a": 0}, "s": {"k": [16, 16], "a": 0}}, {"ty": "fl", "o": {"k": 100, "a": 0}, "c": {"k": [1, 0.9, 0.3, 1], "a": 0}}, {"ty": "tr", "a": {"k": [0, 0], "a": 0}, "p": {"k": [0, 0], "a": 0}, "s": {"a": 1, "k": [{"t": 57, "i": {"x": [1], "y": [1]}, "o": {"x": [0], "y": [0]}, "s": [0, 0]}, {"t": 69, "i": {"x": [1], "y": [1]}, "o": {"x": [0], "y": [0]}, "s": [120, 120]}, {"t": 74, "i": {"x": [1], "y": [1]}, "o": {"x": [0], "y": [0]}, "s": [100, 100]}, {"t": 90, "s": [100, 100]}]}, "r": {"k": 0, "a": 0}, "o": {"a": 1, "k": [{"t": 57, "i": {"x": [1], "y": [1]}, "o": {"x": [0], "y": [0]}, "s": [0]}, {"t": 67, "i": {"x": [1], "y": [1]}, "o": {"x": [0], "y": [0]}, "s": [100]}, {"t": 90, "s": [100]}]}, "sk": {"k": 0, "a": 0}, "sa": {"k": 0, "a": 0}}]}]}, {"ddd": 0, "ty": 4, "ind": 22, "sr": 1, "ip": 0, "op": 90, "st": 0, "ks": {"a": {"k": [0, 0], "a": 0}, "p": {"k": [0, 0], "a": 0}, "s": {"k": [100, 100], "a": 0}, "r": {"k": 0, "a": 0}, "o": {"k": 100, "a": 0}, "sk": {"k": 0, "a": 0}, "sa": {"k": 0, "a": 0}}, "ao": 0, "bm": 0, "shapes": [{"ty": "gr", "it": [{"ty": "el", "d": 1, "p": {"k": [225, 92], "a": 0}, "s": {"k": [16, 16], "a": 0}}, {"ty": "fl", "o": {"k": 100, "a": 0}, "c": {"k": [1, 0.9, 0.3, 1], "a": 0}}, {"ty": "tr", "a": {"k": [0, 0], "a": 0}, "p": {"k": [0, 0], "a": 0}, "s": {"a": 1, "k": [{"t": 45, "i": {"x": [1], "y": [1]}, "o": {"x": [0], "y": [0]}, "s": [0, 0]}, {"t": 57, "i": {"x": [1], "y": [1]}, "o": {"x": [0], "y": [0]}, "s": [120, 120]}, {"t": 62, "i": {"x": [1], "y": [1]}, "o": {"x": [0], "y": [0]}, "s": [100, 100]}, {"t": 90, "s": [100, 100]}]}, "r": {"k": 0, "a": 0}, "o": {"a": 1, "k": [{"t": 45, "i": {"x": [1], "y": [1]}, "o": {"x": [0], "y": [0]}, "s": [0]}, {"t": 55, "i": {"x": [1], "y": [1]}, "o": {"x": [0], "y": [0]}, "s": [100]}, {"t": 90, "s": [100]}]}, "sk": {"k": 0, "a": 0}, "sa": {"k": 0, "a": 0}}]}]}, {"ddd": 0, "ty": 4, "ind": 23, "sr": 1, "ip": 0, "op": 90, "st": 0, "ks": {"a": {"k": [0, 0], "a": 0}, "p": {"k": [0, 0], "a": 0}, "s": {"k": [100, 100], "a": 0}, "r": {"k": 0, "a": 0}, "o": {"k": 100, "a": 0}, "sk": {"k": 0, "a": 0}, "sa": {"k": 0, "a": 0}}, "ao": 0, "bm": 0, "shapes": [{"ty": "gr", "it": [{"ty": "el", "d": 1, "p": {"k": [200, 82], "a": 0}, "s": {"k": [16, 16], "a": 0}}, {"ty": "fl", "o": {"k": 100, "a": 0}, "c": {"k": [1, 0.9, 0.3, 1], "a": 0}}, {"ty": "tr", "a": {"k": [0, 0], "a": 0}, "p": {"k": [0, 0], "a": 0}, "s": {"a": 1, "k": [{"t": 53, "i": {"x": [1], "y": [1]}, "o": {"x": [0], "y": [0]}, "s": [0, 0]}, {"t": 65, "i": {"x": [1], "y": [1]}, "o": {"x": [0], "y": [0]}, "s": [120, 120]}, {"t": 70, "i": {"x": [1], "y": [1]}, "o": {"x": [0], "y": [0]}, "s": [100, 100]}, {"t": 90, "s": [100, 100]}]}, "r": {"k": 0, "a": 0}, "o": {"a": 1, "k": [{"t": 53, "i": {"x": [1], "y": [1]}, "o": {"x": [0], "y": [0]}, "s": [0]}, {"t": 63, "i": {"x": [1], "y": [1]}, "o": {"x": [0], "y": [0]}, "s": [100]}, {"t": 90, "s": [100]}]}, "sk": {"k": 0, "a": 0}, "sa": {"k": 0, "a": 0}}]}]}, {"ddd": 0, "ty": 4, "ind": 24, "sr": 1, "ip": 0, "op": 90, "st": 0, "ks": {"a": {"k": [0, 0], "a": 0}, "p": {"k": [0, 0], "a": 0}, "s": {"k": [100, 100], "a": 0}, "r": {"k": 0, "a": 0}, "o": {"k": 100, "a": 0}, "sk": {"k": 0, "a": 0}, "sa": {"k": 0, "a": 0}}, "ao": 0, "bm": 0, "shapes": [{"ty": "gr", "it": [{"ty": "el", "d": 1, "p": {"k": [148, 95], "a": 0}, "s": {"k": [16, 16], "a": 0}}, {"ty": "fl", "o": {"k": 100, "a": 0}, "c": {"k": [1, 0.9, 0.3, 1], "a": 0}}, {"ty": "tr", "a": {"k": [0, 0], "a": 0}, "p": {"k": [0, 0], "a": 0}, "s": {"a": 1, "k": [{"t": 61, "i": {"x": [1], "y": [1]}, "o": {"x": [0], "y": [0]}, "s": [0, 0]}, {"t": 73, "i": {"x": [1], "y": [1]}, "o": {"x": [0], "y": [0]}, "s": [120, 120]}, {"t": 78, "i": {"x": [1], "y": [1]}, "o": {"x": [0], "y": [0]}, "s": [100, 100]}, {"t": 90, "s": [100, 100]}]}, "r": {"k": 0, "a": 0}, "o": {"a": 1, "k": [{"t": 61, "i": {"x": [1], "y": [1]}, "o": {"x": [0], "y": [0]}, "s": [0]}, {"t": 71, "i": {"x": [1], "y": [1]}, "o": {"x": [0], "y": [0]}, "s": [100]}, {"t": 90, "s": [100]}]}, "sk": {"k": 0, "a": 0}, "sa": {"k": 0, "a": 0}}]}]}, {"ddd": 0, "ty": 4, "ind": 25, "sr": 1, "ip": 0, "op": 90, "st": 0, "ks": {"a": {"k": [0, 0], "a": 0}, "p": {"k": [0, 0], "a": 0}, "s": {"k": [100, 100], "a": 0}, "r": {"k": 0, "a": 0}, "o": {"k": 100, "a": 0}, "sk": {"k": 0, "a": 0}, "sa": {"k": 0, "a": 0}}, "ao": 0, "bm": 0, "shapes": [{"ty": "gr", "it": [{"ty": "el", "d": 1, "p": {"k": [252, 100], "a": 0}, "s": {"k": [16, 16], "a": 0}}, {"ty": "fl", "o": {"k": 100, "a": 0}, "c": {"k": [1, 0.9, 0.3, 1], "a": 0}}, {"ty": "tr", "a": {"k": [0, 0], "a": 0}, "p": {"k": [0, 0], "a": 0}, "s": {"a": 1, "k": [{"t": 37, "i": {"x": [1], "y": [1]}, "o": {"x": [0], "y": [0]}, "s": [0, 0]}, {"t": 49, "i": {"x": [1], "y": [1]}, "o": {"x": [0], "y": [0]}, "s": [120, 120]}, {"t": 54, "i": {"x": [1], "y": [1]}, "o": {"x": [0], "y": [0]}, "s": [100, 100]}, {"t": 90, "s": [100, 100]}]}, "r": {"k": 0, "a": 0}, "o": {"a": 1, "k": [{"t": 37, "i": {"x": [1], "y": [1]}, "o": {"x": [0], "y": [0]}, "s": [0]}, {"t": 47, "i": {"x": [1], "y": [1]}, "o": {"x": [0], "y": [0]}, "s": [100]}, {"t": 90, "s": [100]}]}, "sk": {"k": 0, "a": 0}, "sa": {"k": 0, "a": 0}}]}]}], "v": "5.5.2", "fr": 30, "ip": 0, "op": 90, "w": 400, "h": 400, "ddd": 0, "assets": []}